Workbook

Sheet Leia-me
B2: Matriz de Prioridades das Atividades do ClickUp
B3: Projeto Next · Processos · lista "Implantação de Melhorias (5W2H)" · proposta para validação
B5: Para que serve | C5: Dar uma nota de importância a cada atividade aberta do ClickUp e traduzir a nota em 4 categorias: 1 Baixa, 2 Normal, 3 Alta, 4 Urgente. A prioridade que hoje está no ClickUp NÃO foi usada.
B6: A ideia em uma frase | C6: Importância é uma coisa, prazo é outra e esforço é outra. A nota mede só a importância. O esforço e o prazo servem para ordenar as atividades dentro de cada categoria.
B7: Como a nota é calculada | C7: 1) Cada atividade recebe nota de 1 a 5 em 5 critérios (aba Matriz). 2) A média é ponderada pelos pesos da aba Matriz. 3) Multiplica-se pelo fator do processo (aba Processos): um ajuste pequeno, de 0,9 a 1,1. 4) Soma-se o ajuste da natureza da ação (controle sobe, indicador desce). 5) A nota final vira categoria pelos cortes da aba Matriz. 6) Duas regras passam por cima da conta (vetos): risco de fraude nota 5 vira, no mínimo, Alta; atividade que para a obra ou o repasse da CEF vira Urgente.
B8: Como usar a aba Tarefas | C8: 1) Preencha as células amarelas: esforço (H), as 5 notas (I a M) e, se for o caso, "Para obra ou repasse CEF?" (N). 2) As colunas cinza calculam sozinhas: nota, categoria e prioridade. 3) A coluna "Ordem geral" diz o que fazer primeiro: categoria, depois nota, depois menor esforço. 4) Dá para filtrar por processo, responsável, status ou prioridade.
B9: Cores | C9: Texto azul em fundo amarelo = pode editar (pesos, cortes, notas, esforço). Fundo cinza = fórmula, não editar. Fundo azul-escuro = títulos.
B10: O que é proposta minha | C10: Todos os pesos, cortes, ajustes e médias de processo são PROPOSTA para validar. Nenhum veio de dado oficial. As notas das 12 atividades marcadas como "Âncora (proposta)" também são minhas: servem de exemplo e de referência para calibrar. Troque qualquer valor azul e tudo recalcula.
B11: Fonte dos dados | C11: ClickUp, lista "Implantação de Melhorias (5W2H)", lida em 21/10/2026. Entram 401 atividades abertas (status: sem prazo definido, em progresso, em atraso e pausado). Ficam de fora as concluídas e as canceladas. Processo e Tipo de Ação vêm dos campos do ClickUp; onde o campo estava vazio usei a etiqueta; sem nenhum dos dois ficou "Sem processo definido".
B12: Sugestões automáticas | C12: A coluna "Natureza" (Controle, Documento normativo, etc.) é uma sugestão minha a partir do tipo de ação do ClickUp e de palavras do nome da tarefa. Revise e troque pela lista suspensa se estiver errada.
B13: Limites | C13: A planilha não altera nada no ClickUp. As notas dos critérios (colunas I a M) ficam em branco para as áreas e o Processos pontuarem, exceto nas âncoras.

Sheet Matriz
A1: Matriz de critérios, pesos e regras
A2: Células azuis em fundo amarelo podem ser editadas. Pesos e cortes são proposta.
A4: Critério | B4: Pergunta | C4: Peso (%) | D4: Nota 1 | E4: Nota 2 | F4: Nota 3 | G4: Nota 4 | H4: Nota 5
A5: Risco de fraude e erro | B5: Pode haver desvio de dinheiro ou erro grave sem que alguém perceba? | C5: 30 | D5: Nenhum risco relevante. | E5: Erro pequeno e fácil de achar. | F5: Erro ou desvio possível, mas há conferência depois. | G5: Desvio ou erro de valor possível e sem barreira clara. | H5: Dinheiro sai ou dado crítico muda sem trava, aprovação ou conferência.
A6: Impacto financeiro | B6: Quanto dinheiro está em jogo ou pode ser perdido ou ganho? | C6: 20 | D6: Sem efeito em caixa. | E6: Efeito pequeno (exemplo: até R$ 10 mil). | F6: Efeito médio (exemplo: R$ 10 a 50 mil). | G6: Efeito grande (exemplo: R$ 50 a 200 mil). | H6: Efeito muito grande (exemplo: acima de R$ 200 mil). Faixas a confirmar com o Financeiro.
A7: Impacto na obra e na entrega | B7: Atrasa obra, lançamento, repasse ou entrega? | C7: 20 | D7: Nenhum efeito. | E7: Atrasa rotina interna. | F7: Atrasa uma etapa, sem afetar marco. | G7: Pode atrasar marco de obra ou de lançamento. | H7: Para a obra, o repasse da CEF ou a entrega.
A8: Exigência legal, CEF e compliance | B8: Existe lei, norma, contrato, CEF ou LGPD exigindo isso? | C8: 15 | D8: Nenhuma. | E8: Boa prática interna. | F8: Exigência interna formal (política, procedimento). | G8: Exigência de contrato, CEF ou LGPD. | H8: Lei, norma de segurança ou risco de multa ou embargo.
A9: Dependência | B9: Outras atividades ou áreas esperam por esta? | C9: 15 | D9: Ninguém espera. | E9: Uma atividade espera. | F9: Duas ou três atividades, ou uma área. | G9: Várias áreas esperam. | H9: Destrava um processo inteiro ou vários fluxos.
A10: Soma dos pesos | B10: =IF(C10=100,"Soma correta (100%)","ATENÇÃO: os pesos devem somar 100") -> Soma correta (100%) | C10: =SUM(C5:C9) -> 100
A12: Esforço (não entra na nota) | B12: Quanto custa fazer? Só ordena dentro da categoria e marca ganho rápido. | C12: — | D12: Nível 1: Até 1 semana. | E12: Nível 2: Até 1 mês. | F12: Nível 3: Até 3 meses. | G12: Nível 4: Mais de 3 meses. | H12: Nível 5: Depende de contratação, sistema externo ou decisão da diretoria.
A14: Cortes das categorias
A15: Categoria | B15: Significado | C15: Nota mínima (≥)
A16: 1 · Baixa | B16: Pode esperar. Fazer quando houver folga. | C16: 0
A17: 2 · Normal | B17: Entra na rotina de melhoria. | C17: 2.5
A18: 3 · Alta | B18: Planejar para o próximo ciclo. | C18: 3.3
A19: 4 · Urgente | B19: Tratar já, com dono e prazo. | C19: 4
A21: Regras que passam por cima da conta (vetos)
A22: Regra | B22: Quando vale | C22: Categoria mínima
A23: Risco no nível máximo | B23: A nota de "Risco de fraude e erro" é 5. | C23: 3
A24: Para obra ou repasse da CEF | B24: Coluna N da aba Tarefas marcada como "Sim". | C24: 4
A26: Ajuste por natureza da ação (somado à nota)
A27: Natureza | B27: Quando usar | C27: Ajuste
A28: Controle | B28: Alçada, trava, segregação, aprovação, conciliação, acesso. Protege contra fraude e erro. | C28: 0.3
A29: Documento normativo | B29: POP, IT, Política ou Regimento. A nota vem do risco que o documento cobre. | C29: 0
A30: Automação ou sistema | B30: Integração, parametrização, campo, módulo. A nota vem do que protege ou acelera. | C30: 0
A31: Definição ou decisão | B31: Definir regra, responsável ou prazo, ou avaliar uma opção. | C31: 0
A32: Treinamento | B32: Treinar equipe. Sobe a nota pelos critérios quando sustenta um controle. | C32: -0.2
A33: Indicador | B33: Medir sem proteger. Se o indicador detecta desvio (exemplo: avanço físico x financeiro), classificar como Controle. | C33: -0.3
A35: Nota final = média ponderada dos 5 critérios × fator do processo + ajuste da natureza. Depois aplicam-se os vetos. Esforço e prazo só ordenam.

Sheet Processos
A1: Peso dos processos (cadeia de valor)
A2: Três perguntas, de 1 a 5, por processo. O fator é um ajuste pequeno sobre a nota; o risco da atividade manda mais do que o processo.
A4: Fator mínimo | B4: 0.9
A5: Fator máximo | B5: 1.1
A7: Processo | B7: Dinheiro (1–5) | C7: Dependência (1–5) | D7: Irreversibilidade (1–5) | E7: Média | F7: Fator | G7: Por quê (hipótese para validar)
A8: Incorporação Make It | B8: 5 | C8: 5 | D8: 5 | E8: =ROUND(AVERAGE(B8:D8),2) -> 5 | F8: =ROUND($B$4+($B$5-$B$4)*(E8-1)/4,3) -> 1.1 | G8: Define produto, projeto e custo. Quase tudo depende e o erro volta caro.
A9: Incorporação Gadens | B9: 5 | C9: 5 | D9: 5 | E9: =ROUND(AVERAGE(B9:D9),2) -> 5 | F9: =ROUND($B$4+($B$5-$B$4)*(E9-1)/4,3) -> 1.1 | G9: Mesma lógica; ciclo mais longo e valor por unidade maior.
A10: Engenharia | B10: 5 | C10: 5 | D10: 4 | E10: =ROUND(AVERAGE(B10:D10),2) -> 4.67 | F10: =ROUND($B$4+($B$5-$B$4)*(E10-1)/4,3) -> 1.084 | G10: Orçamento, planejamento e obra concentram o maior custo e o caminho crítico.
A11: Novos Negócios | B11: 5 | C11: 3 | D11: 5 | E11: =ROUND(AVERAGE(B11:D11),2) -> 4.33 | F11: =ROUND($B$4+($B$5-$B$4)*(E11-1)/4,3) -> 1.067 | G11: Poucas decisões, mas irreversíveis (compra de terreno, contratos, SPE).
A12: Suprimentos | B12: 5 | C12: 4 | D12: 3 | E12: =ROUND(AVERAGE(B12:D12),2) -> 4 | F12: =ROUND($B$4+($B$5-$B$4)*(E12-1)/4,3) -> 1.05 | G12: Maior parte do custo de obra passa por compras; erro de compra tem correção parcial.
A13: Financeiro | B13: 4 | C13: 5 | D13: 3 | E13: =ROUND(AVERAGE(B13:D13),2) -> 4 | F13: =ROUND($B$4+($B$5-$B$4)*(E13-1)/4,3) -> 1.05 | G13: Todo pagamento e conciliação passa por aqui. É processo de apoio, mas de alto risco.
A14: GMO | B14: 4 | C14: 4 | D14: 3 | E14: =ROUND(AVERAGE(B14:D14),2) -> 3.67 | F14: =ROUND($B$4+($B$5-$B$4)*(E14-1)/4,3) -> 1.034 | G14: Contratos de empreiteiros e medição; a obra depende deles para iniciar e pagar.
A15: Comercial Make It | B15: 4 | C15: 4 | D15: 3 | E15: =ROUND(AVERAGE(B15:D15),2) -> 3.67 | F15: =ROUND($B$4+($B$5-$B$4)*(E15-1)/4,3) -> 1.034 | G15: Caixa depende do ritmo de venda e do repasse da CEF.
A16: Comercial Gadens | B16: 4 | C16: 3 | D16: 3 | E16: =ROUND(AVERAGE(B16:D16),2) -> 3.33 | F16: =ROUND($B$4+($B$5-$B$4)*(E16-1)/4,3) -> 1.017 | G16: Ciclo mais lento e com mais folga que o Make It.
A17: Sem processo definido | B17: 3 | C17: 3 | D17: 3 | E17: =ROUND(AVERAGE(B17:D17),2) -> 3 | F17: =ROUND($B$4+($B$5-$B$4)*(E17-1)/4,3) -> 1 | G17: Atividade sem Processo nem etiqueta no ClickUp. Fator neutro.

Sheet Resumo
A1: Resumo da priorização
A2: Tudo calculado a partir da aba Tarefas.
A4: Atividades abertas | B4: =COUNTA(Tarefas!$A$5:$A$405) -> 401
A5: Já pontuadas | B5: =COUNT(Tarefas!$R$5:$R$405) -> 12
A6: Falta pontuar | B6: =B4-B5 -> 389
A8: Prioridade | B8: Quantidade | C8: % das pontuadas | D8: Meta máxima | E8: Situação
A9: 4 · Urgente | B9: =COUNTIF(Tarefas!$T$5:$T$405,4) -> 2 | C9: =IF($B$5=0,0,B9/$B$5) -> 0.16666667 | D9: 0.1 | E9: =IF($B$5=0,"—",IF(C9>D9,"Acima da meta: revisar cortes","Dentro da meta")) -> Acima da meta: revisar cortes
A10: 3 · Alta | B10: =COUNTIF(Tarefas!$T$5:$T$405,3) -> 6 | C10: =IF($B$5=0,0,B10/$B$5) -> 0.5 | D10: 0.25 | E10: =IF($B$5=0,"—",IF(C10>D10,"Acima da meta: revisar cortes","Dentro da meta")) -> Acima da meta: revisar cortes
A11: 2 · Normal | B11: =COUNTIF(Tarefas!$T$5:$T$405,2) -> 2 | C11: =IF($B$5=0,0,B11/$B$5) -> 0.16666667 | D11: — | E11: —
A12: 1 · Baixa | B12: =COUNTIF(Tarefas!$T$5:$T$405,1) -> 2 | C12: =IF($B$5=0,0,B12/$B$5) -> 0.16666667 | D12: — | E12: —
A13: Meta máxima: se Urgente passar de 10% ou Alta de 25% das pontuadas, a escala perde sentido. É proposta; edite as células azuis.
A15: Processo | B15: Abertas | C15: Pontuadas | D15: Urgente | E15: Alta | F15: Normal | G15: Baixa
A16: Incorporação Make It | B16: =COUNTIF(Tarefas!$C$5:$C$405,A16) -> 16 | C16: =COUNTIFS(Tarefas!$C$5:$C$405,A16,Tarefas!$R$5:$R$405,">0") -> 0 | D16: =COUNTIFS(Tarefas!$C$5:$C$405,$A16,Tarefas!$T$5:$T$405,4) -> 0 | E16: =COUNTIFS(Tarefas!$C$5:$C$405,$A16,Tarefas!$T$5:$T$405,3) -> 0 | F16: =COUNTIFS(Tarefas!$C$5:$C$405,$A16,Tarefas!$T$5:$T$405,2) -> 0 | G16: =COUNTIFS(Tarefas!$C$5:$C$405,$A16,Tarefas!$T$5:$T$405,1) -> 0
A17: Incorporação Gadens | B17: =COUNTIF(Tarefas!$C$5:$C$405,A17) -> 12 | C17: =COUNTIFS(Tarefas!$C$5:$C$405,A17,Tarefas!$R$5:$R$405,">0") -> 0 | D17: =COUNTIFS(Tarefas!$C$5:$C$405,$A17,Tarefas!$T$5:$T$405,4) -> 0 | E17: =COUNTIFS(Tarefas!$C$5:$C$405,$A17,Tarefas!$T$5:$T$405,3) -> 0 | F17: =COUNTIFS(Tarefas!$C$5:$C$405,$A17,Tarefas!$T$5:$T$405,2) -> 0 | G17: =COUNTIFS(Tarefas!$C$5:$C$405,$A17,Tarefas!$T$5:$T$405,1) -> 0
A18: Engenharia | B18: =COUNTIF(Tarefas!$C$5:$C$405,A18) -> 81 | C18: =COUNTIFS(Tarefas!$C$5:$C$405,A18,Tarefas!$R$5:$R$405,">0") -> 2 | D18: =COUNTIFS(Tarefas!$C$5:$C$405,$A18,Tarefas!$T$5:$T$405,4) -> 1 | E18: =COUNTIFS(Tarefas!$C$5:$C$405,$A18,Tarefas!$T$5:$T$405,3) -> 1 | F18: =COUNTIFS(Tarefas!$C$5:$C$405,$A18,Tarefas!$T$5:$T$405,2) -> 0 | G18: =COUNTIFS(Tarefas!$C$5:$C$405,$A18,Tarefas!$T$5:$T$405,1) -> 0
A19: Novos Negócios | B19: =COUNTIF(Tarefas!$C$5:$C$405,A19) -> 30 | C19: =COUNTIFS(Tarefas!$C$5:$C$405,A19,Tarefas!$R$5:$R$405,">0") -> 1 | D19: =COUNTIFS(Tarefas!$C$5:$C$405,$A19,Tarefas!$T$5:$T$405,4) -> 1 | E19: =COUNTIFS(Tarefas!$C$5:$C$405,$A19,Tarefas!$T$5:$T$405,3) -> 0 | F19: =COUNTIFS(Tarefas!$C$5:$C$405,$A19,Tarefas!$T$5:$T$405,2) -> 0 | G19: =COUNTIFS(Tarefas!$C$5:$C$405,$A19,Tarefas!$T$5:$T$405,1) -> 0
A20: Suprimentos | B20: =COUNTIF(Tarefas!$C$5:$C$405,A20) -> 35 | C20: =COUNTIFS(Tarefas!$C$5:$C$405,A20,Tarefas!$R$5:$R$405,">0") -> 2 | D20: =COUNTIFS(Tarefas!$C$5:$C$405,$A20,Tarefas!$T$5:$T$405,4) -> 0 | E20: =COUNTIFS(Tarefas!$C$5:$C$405,$A20,Tarefas!$T$5:$T$405,3) -> 1 | F20: =COUNTIFS(Tarefas!$C$5:$C$405,$A20,Tarefas!$T$5:$T$405,2) -> 1 | G20: =COUNTIFS(Tarefas!$C$5:$C$405,$A20,Tarefas!$T$5:$T$405,1) -> 0
A21: Financeiro | B21: =COUNTIF(Tarefas!$C$5:$C$405,A21) -> 44 | C21: =COUNTIFS(Tarefas!$C$5:$C$405,A21,Tarefas!$R$5:$R$405,">0") -> 4 | D21: =COUNTIFS(Tarefas!$C$5:$C$405,$A21,Tarefas!$T$5:$T$405,4) -> 0 | E21: =COUNTIFS(Tarefas!$C$5:$C$405,$A21,Tarefas!$T$5:$T$405,3) -> 3 | F21: =COUNTIFS(Tarefas!$C$5:$C$405,$A21,Tarefas!$T$5:$T$405,2) -> 0 | G21: =COUNTIFS(Tarefas!$C$5:$C$405,$A21,Tarefas!$T$5:$T$405,1) -> 1
A22: GMO | B22: =COUNTIF(Tarefas!$C$5:$C$405,A22) -> 75 | C22: =COUNTIFS(Tarefas!$C$5:$C$405,A22,Tarefas!$R$5:$R$405,">0") -> 0 | D22: =COUNTIFS(Tarefas!$C$5:$C$405,$A22,Tarefas!$T$5:$T$405,4) -> 0 | E22: =COUNTIFS(Tarefas!$C$5:$C$405,$A22,Tarefas!$T$5:$T$405,3) -> 0 | F22: =COUNTIFS(Tarefas!$C$5:$C$405,$A22,Tarefas!$T$5:$T$405,2) -> 0 | G22: =COUNTIFS(Tarefas!$C$5:$C$405,$A22,Tarefas!$T$5:$T$405,1) -> 0
A23: Comercial Make It | B23: =COUNTIF(Tarefas!$C$5:$C$405,A23) -> 47 | C23: =COUNTIFS(Tarefas!$C$5:$C$405,A23,Tarefas!$R$5:$R$405,">0") -> 0 | D23: =COUNTIFS(Tarefas!$C$5:$C$405,$A23,Tarefas!$T$5:$T$405,4) -> 0 | E23: =COUNTIFS(Tarefas!$C$5:$C$405,$A23,Tarefas!$T$5:$T$405,3) -> 0 | F23: =COUNTIFS(Tarefas!$C$5:$C$405,$A23,Tarefas!$T$5:$T$405,2) -> 0 | G23: =COUNTIFS(Tarefas!$C$5:$C$405,$A23,Tarefas!$T$5:$T$405,1) -> 0
A24: Comercial Gadens | B24: =COUNTIF(Tarefas!$C$5:$C$405,A24) -> 60 | C24: =COUNTIFS(Tarefas!$C$5:$C$405,A24,Tarefas!$R$5:$R$405,">0") -> 3 | D24: =COUNTIFS(Tarefas!$C$5:$C$405,$A24,Tarefas!$T$5:$T$405,4) -> 0 | E24: =COUNTIFS(Tarefas!$C$5:$C$405,$A24,Tarefas!$T$5:$T$405,3) -> 1 | F24: =COUNTIFS(Tarefas!$C$5:$C$405,$A24,Tarefas!$T$5:$T$405,2) -> 1 | G24: =COUNTIFS(Tarefas!$C$5:$C$405,$A24,Tarefas!$T$5:$T$405,1) -> 1
A25: Sem processo definido | B25: =COUNTIF(Tarefas!$C$5:$C$405,A25) -> 1 | C25: =COUNTIFS(Tarefas!$C$5:$C$405,A25,Tarefas!$R$5:$R$405,">0") -> 0 | D25: =COUNTIFS(Tarefas!$C$5:$C$405,$A25,Tarefas!$T$5:$T$405,4) -> 0 | E25: =COUNTIFS(Tarefas!$C$5:$C$405,$A25,Tarefas!$T$5:$T$405,3) -> 0 | F25: =COUNTIFS(Tarefas!$C$5:$C$405,$A25,Tarefas!$T$5:$T$405,2) -> 0 | G25: =COUNTIFS(Tarefas!$C$5:$C$405,$A25,Tarefas!$T$5:$T$405,1) -> 0
A26: Total | B26: =SUM(B16:B25) -> 401 | C26: =SUM(C16:C25) -> 12 | D26: =SUM(D16:D25) -> 2 | E26: =SUM(E16:E25) -> 6 | F26: =SUM(F16:F25) -> 2 | G26: =SUM(G16:G25) -> 2

Sheet Tarefas
A1: Atividades abertas do ClickUp com a matriz
A2: Preencha as células amarelas (H a N). Colunas cinza calculam sozinhas. Âncoras: 12 atividades já pontuadas como proposta, para calibrar.
A4: ID | B4: Tarefa | C4: Processo | D4: Responsável | E4: Status | F4: Prazo | G4: Natureza | H4: Esforço (1–5) | I4: Risco de fraude e erro | J4: Impacto financeiro | K4: Obra e entrega | L4: Legal, CEF e compliance | M4: Dependência | N4: Para obra ou repasse CEF? | O4: Média ponderada | P4: Fator do processo | Q4: Ajuste da natureza | R4: Nota final | S4: Categoria pela nota | T4: Categoria final | U4: Prioridade | V4: Chave | W4: Ordem geral | X4: Origem da nota | Y4: Por que (âncora) | Z4: Calibração
A5: 17tpepcgqnk | B5: Avaliar análise de crédito complementar na modalidade associativo | C5: Comercial Gadens | D5: Érica Ferreira Tavares Silva Caldeira, Cleverton Parnoff | E5: em progresso | F5: 46387 | G5: Definição ou decisão | O5: =IF(COUNT(I5:M5)<5,"",ROUND((I5*Matriz!$C$5+J5*Matriz!$C$6+K5*Matriz!$C$7+L5*Matriz!$C$8+M5*Matriz!$C$9)/SUM(Matriz!$C$5:$C$9),2)) | P5: =IFERROR(INDEX(Processos!$F$8:$F$17,MATCH(C5,Processos!$A$8:$A$17,0)),1) -> 1.017 | Q5: =IFERROR(INDEX(Matriz!$C$28:$C$33,MATCH(G5,Matriz!$A$28:$A$33,0)),0) -> 0 | R5: =IF(O5="","",ROUND(O5*P5+Q5,2)) | S5: =IF(R5="","",IF(R5>=Matriz!$C$19,4,IF(R5>=Matriz!$C$18,3,IF(R5>=Matriz!$C$17,2,1)))) | T5: =IF(S5="","",MAX(S5,IF(I5=5,Matriz!$C$23,0),IF(N5="Sim",Matriz!$C$24,0))) | U5: =IF(T5="","",CHOOSE(T5,"Baixa","Normal","Alta","Urgente")) | V5: =IF(T5="","",T5*1000+R5*10-IF(H5="",3,H5)/10-ROW()/1000000) | W5: =IF(V5="","",COUNTIF($V$5:$V$405,">"&V5)+1)
A6: 17tpepcgqnn | B6: Avaliar análise de crédito complementar na modalidade bancário | C6: Comercial Gadens | D6: Érica Ferreira Tavares Silva Caldeira, Cleverton Parnoff | E6: em progresso | F6: 46387 | G6: Definição ou decisão | O6: =IF(COUNT(I6:M6)<5,"",ROUND((I6*Matriz!$C$5+J6*Matriz!$C$6+K6*Matriz!$C$7+L6*Matriz!$C$8+M6*Matriz!$C$9)/SUM(Matriz!$C$5:$C$9),2)) | P6: =IFERROR(INDEX(Processos!$F$8:$F$17,MATCH(C6,Processos!$A$8:$A$17,0)),1) -> 1.017 | Q6: =IFERROR(INDEX(Matriz!$C$28:$C$33,MATCH(G6,Matriz!$A$28:$A$33,0)),0) -> 0 | R6: =IF(O6="","",ROUND(O6*P6+Q6,2)) | S6: =IF(R6="","",IF(R6>=Matriz!$C$19,4,IF(R6>=Matriz!$C$18,3,IF(R6>=Matriz!$C$17,2,1)))) | T6: =IF(S6="","",MAX(S6,IF(I6=5,Matriz!$C$23,0),IF(N6="Sim",Matriz!$C$24,0))) | U6: =IF(T6="","",CHOOSE(T6,"Baixa","Normal","Alta","Urgente")) | V6: =IF(T6="","",T6*1000+R6*10-IF(H6="",3,H6)/10-ROW()/1000000) | W6: =IF(V6="","",COUNTIF($V$5:$V$405,">"&V6)+1)
A7: 17tpepcdam9 | B7: Conceder acesso aos sistemas SPC e Serasa | C7: Comercial Gadens | D7: Cleverton Parnoff | E7: em progresso | F7: 46326 | G7: Controle | O7: =IF(COUNT(I7:M7)<5,"",ROUND((I7*Matriz!$C$5+J7*Matriz!$C$6+K7*Matriz!$C$7+L7*Matriz!$C$8+M7*Matriz!$C$9)/SUM(Matriz!$C$5:$C$9),2)) | P7: =IFERROR(INDEX(Processos!$F$8:$F$17,MATCH(C7,Processos!$A$8:$A$17,0)),1) -> 1.017 | Q7: =IFERROR(INDEX(Matriz!$C$28:$C$33,MATCH(G7,Matriz!$A$28:$A$33,0)),0) -> 0.3 | R7: =IF(O7="","",ROUND(O7*P7+Q7,2)) | S7: =IF(R7="","",IF(R7>=Matriz!$C$19,4,IF(R7>=Matriz!$C$18,3,IF(R7>=Matriz!$C$17,2,1)))) | T7: =IF(S7="","",MAX(S7,IF(I7=5,Matriz!$C$23,0),IF(N7="Sim",Matriz!$C$24,0))) | U7: =IF(T7="","",CHOOSE(T7,"Baixa","Normal","Alta","Urgente")) | V7: =IF(T7="","",T7*1000+R7*10-IF(H7="",3,H7)/10-ROW()/1000000) | W7: =IF(V7="","",COUNTIF($V$5:$V$405,">"&V7)+1)
A8: 17tpepcdg1y | B8: Definir periodicidade de limpeza das unidades de estoque vazias - Monica; | C8: Comercial Gadens | D8: Mônica Massaneiro | E8: em progresso | F8: 46326 | G8: Definição ou decisão | O8: =IF(COUNT(I8:M8)<5,"",ROUND((I8*Matriz!$C$5+J8*Matriz!$C$6+K8*Matriz!$C$7+L8*Matriz!$C$8+M8*Matriz!$C$9)/SUM(Matriz!$C$5:$C$9),2)) | P8: =IFERROR(INDEX(Processos!$F$8:$F$17,MATCH(C8,Processos!$A$8:$A$17,0)),1) -> 1.017 | Q8: =IFERROR(INDEX(Matriz!$C$28:$C$33,MATCH(G8,Matriz!$A$28:$A$33,0)),0) -> 0 | R8: =IF(O8="","",ROUND(O8*P8+Q8,2)) | S8: =IF(R8="","",IF(R8>=Matriz!$C$19,4,IF(R8>=Matriz!$C$18,3,IF(R8>=Matriz!$C$17,2,1)))) | T8: =IF(S8="","",MAX(S8,IF(I8=5,Matriz!$C$23,0),IF(N8="Sim",Matriz!$C$24,0))) | U8: =IF(T8="","",CHOOSE(T8,"Baixa","Normal","Alta","Urgente")) | V8: =IF(T8="","",T8*1000+R8*10-IF(H8="",3,H8)/10-ROW()/1000000) | W8: =IF(V8="","",COUNTIF($V$5:$V$405,">"&V8)+1)
A9: 17tpepcdk0j | B9: Definição de alçada de aprovação das vendas | C9: Comercial Gadens | D9: Mônica Massaneiro | E9: em progresso | F9: 46356 | G9: Controle | O9: =IF(COUNT(I9:M9)<5,"",ROUND((I9*Matriz!$C$5+J9*Matriz!$C$6+K9*Matriz!$C$7+L9*Matriz!$C$8+M9*Matriz!$C$9)/SUM(Matriz!$C$5:$C$9),2)) | P9: =IFERROR(INDEX(Processos!$F$8:$F$17,MATCH(C9,Processos!$A$8:$A$17,0)),1) -> 1.017 | Q9: =IFERROR(INDEX(Matriz!$C$28:$C$33,MATCH(G9,Matriz!$A$28:$A$33,0)),0) -> 0.3 | R9: =IF(O9="","",ROUND(O9*P9+Q9,2)) | S9: =IF(R9="","",IF(R9>=Matriz!$C$19,4,IF(R9>=Matriz!$C$18,3,IF(R9>=Matriz!$C$17,2,1)))) | T9: =IF(S9="","",MAX(S9,IF(I9=5,Matriz!$C$23,0),IF(N9="Sim",Matriz!$C$24,0))) | U9: =IF(T9="","",CHOOSE(T9,"Baixa","Normal","Alta","Urgente")) | V9: =IF(T9="","",T9*1000+R9*10-IF(H9="",3,H9)/10-ROW()/1000000) | W9: =IF(V9="","",COUNTIF($V$5:$V$405,">"&V9)+1)
A10: 17tpepcgq44 | B10: Elaborar Fluxo - Tapumes | C10: Comercial Gadens | D10: Andrei Souza Santos | E10: em progresso | F10: 46387 | G10: Definição ou decisão | O10: =IF(COUNT(I10:M10)<5,"",ROUND((I10*Matriz!$C$5+J10*Matriz!$C$6+K10*Matriz!$C$7+L10*Matriz!$C$8+M10*Matriz!$C$9)/SUM(Matriz!$C$5:$C$9),2)) | P10: =IFERROR(INDEX(Processos!$F$8:$F$17,MATCH(C10,Processos!$A$8:$A$17,0)),1) -> 1.017 | Q10: =IFERROR(INDEX(Matriz!$C$28:$C$33,MATCH(G10,Matriz!$A$28:$A$33,0)),0) -> 0 | R10: =IF(O10="","",ROUND(O10*P10+Q10,2)) | S10: =IF(R10="","",IF(R10>=Matriz!$C$19,4,IF(R10>=Matriz!$C$18,3,IF(R10>=Matriz!$C$17,2,1)))) | T10: =IF(S10="","",MAX(S10,IF(I10=5,Matriz!$C$23,0),IF(N10="Sim",Matriz!$C$24,0))) | U10: =IF(T10="","",CHOOSE(T10,"Baixa","Normal","Alta","Urgente")) | V10: =IF(T10="","",T10*1000+R10*10-IF(H10="",3,H10)/10-ROW()/1000000) | W10: =IF(V10="","",COUNTIF($V$5:$V$405,">"&V10)+1)
A11: 17tpepcdg1u | B11: Elaborar POP - Decorados (Incluindo vistoria de decorados) - Mariane; | C11: Comercial Gadens | D11: Mariane Cristine Machado Scandelari | E11: em progresso | F11: 46356 | G11: Documento normativo | O11: =IF(COUNT(I11:M11)<5,"",ROUND((I11*Matriz!$C$5+J11*Matriz!$C$6+K11*Matriz!$C$7+L11*Matriz!$C$8+M11*Matriz!$C$9)/SUM(Matriz!$C$5:$C$9),2)) | P11: =IFERROR(INDEX(Processos!$F$8:$F$17,MATCH(C11,Processos!$A$8:$A$17,0)),1) -> 1.017 | Q11: =IFERROR(INDEX(Matriz!$C$28:$C$33,MATCH(G11,Matriz!$A$28:$A$33,0)),0) -> 0 | R11: =IF(O11="","",ROUND(O11*P11+Q11,2)) | S11: =IF(R11="","",IF(R11>=Matriz!$C$19,4,IF(R11>=Matriz!$C$18,3,IF(R11>=Matriz!$C$17,2,1)))) | T11: =IF(S11="","",MAX(S11,IF(I11=5,Matriz!$C$23,0),IF(N11="Sim",Matriz!$C$24,0))) | U11: =IF(T11="","",CHOOSE(T11,"Baixa","Normal","Alta","Urgente")) | V11: =IF(T11="","",T11*1000+R11*10-IF(H11="",3,H11)/10-ROW()/1000000) | W11: =IF(V11="","",COUNTIF($V$5:$V$405,">"&V11)+1)
A12: 17tpepcgphn | B12: Elaborar POP - Definição de Tabela de Preço | C12: Comercial Gadens | D12: Mônica Massaneiro | E12: em progresso | F12: 46356 | G12: Documento normativo | O12: =IF(COUNT(I12:M12)<5,"",ROUND((I12*Matriz!$C$5+J12*Matriz!$C$6+K12*Matriz!$C$7+L12*Matriz!$C$8+M12*Matriz!$C$9)/SUM(Matriz!$C$5:$C$9),2)) | P12: =IFERROR(INDEX(Processos!$F$8:$F$17,MATCH(C12,Processos!$A$8:$A$17,0)),1) -> 1.017 | Q12: =IFERROR(INDEX(Matriz!$C$28:$C$33,MATCH(G12,Matriz!$A$28:$A$33,0)),0) -> 0 | R12: =IF(O12="","",ROUND(O12*P12+Q12,2)) | S12: =IF(R12="","",IF(R12>=Matriz!$C$19,4,IF(R12>=Matriz!$C$18,3,IF(R12>=Matriz!$C$17,2,1)))) | T12: =IF(S12="","",MAX(S12,IF(I12=5,Matriz!$C$23,0),IF(N12="Sim",Matriz!$C$24,0))) | U12: =IF(T12="","",CHOOSE(T12,"Baixa","Normal","Alta","Urgente")) | V12: =IF(T12="","",T12*1000+R12*10-IF(H12="",3,H12)/10-ROW()/1000000) | W12: =IF(V12="","",COUNTIF($V$5:$V$405,">"&V12)+1)
A13: 17tpepcdk0k | B13: Elaborar POP - Seleção de Imobiliárias (nível A, B e C) | C13: Comercial Gadens | D13: Mônica Massaneiro | E13: em progresso | F13: 46356 | G13: Documento normativo | O13: =IF(COUNT(I13:M13)<5,"",ROUND((I13*Matriz!$C$5+J13*Matriz!$C$6+K13*Matriz!$C$7+L13*Matriz!$C$8+M13*Matriz!$C$9)/SUM(Matriz!$C$5:$C$9),2)) | P13: =IFERROR(INDEX(Processos!$F$8:$F$17,MATCH(C13,Processos!$A$8:$A$17,0)),1) -> 1.017 | Q13: =IFERROR(INDEX(Matriz!$C$28:$C$33,MATCH(G13,Matriz!$A$28:$A$33,0)),0) -> 0 | R13: =IF(O13="","",ROUND(O13*P13+Q13,2)) | S13: =IF(R13="","",IF(R13>=Matriz!$C$19,4,IF(R13>=Matriz!$C$18,3,IF(R13>=Matriz!$C$17,2,1)))) | T13: =IF(S13="","",MAX(S13,IF(I13=5,Matriz!$C$23,0),IF(N13="Sim",Matriz!$C$24,0))) | U13: =IF(T13="","",CHOOSE(T13,"Baixa","Normal","Alta","Urgente")) | V13: =IF(T13="","",T13*1000+R13*10-IF(H13="",3,H13)/10-ROW()/1000000) | W13: =IF(V13="","",COUNTIF($V$5:$V$405,">"&V13)+1)
A14: 17tpepcdama | B14: Elaborar POP ou Política - Premissas Validação da Análise de Crédito - Gadens | C14: Comercial Gadens | D14: Cleverton Parnoff | E14: em progresso | F14: 46387 | G14: Documento normativo | O14: =IF(COUNT(I14:M14)<5,"",ROUND((I14*Matriz!$C$5+J14*Matriz!$C$6+K14*Matriz!$C$7+L14*Matriz!$C$8+M14*Matriz!$C$9)/SUM(Matriz!$C$5:$C$9),2)) | P14: =IFERROR(INDEX(Processos!$F$8:$F$17,MATCH(C14,Processos!$A$8:$A$17,0)),1) -> 1.017 | Q14: =IFERROR(INDEX(Matriz!$C$28:$C$33,MATCH(G14,Matriz!$A$28:$A$33,0)),0) -> 0 | R14: =IF(O14="","",ROUND(O14*P14+Q14,2)) | S14: =IF(R14="","",IF(R14>=Matriz!$C$19,4,IF(R14>=Matriz!$C$18,3,IF(R14>=Matriz!$C$17,2,1)))) | T14: =IF(S14="","",MAX(S14,IF(I14=5,Matriz!$C$23,0),IF(N14="Sim",Matriz!$C$24,0))) | U14: =IF(T14="","",CHOOSE(T14,"Baixa","Normal","Alta","Urgente")) | V14: =IF(T14="","",T14*1000+R14*10-IF(H14="",3,H14)/10-ROW()/1000000) | W14: =IF(V14="","",COUNTIF($V$5:$V$405,">"&V14)+1)
A15: 17tpepcgphp | B15: Elaborar Política - Política Comercial do Empreendimento (Prazo, Condição de Pagamento, Riscos, modalidade e fonte de recurso, campanhas por empreendimento, etc.), depois, elaborar POP | C15: Comercial Gadens | D15: Mônica Massaneiro | E15: em progresso | F15: 46446 | G15: Documento normativo | O15: =IF(COUNT(I15:M15)<5,"",ROUND((I15*Matriz!$C$5+J15*Matriz!$C$6+K15*Matriz!$C$7+L15*Matriz!$C$8+M15*Matriz!$C$9)/SUM(Matriz!$C$5:$C$9),2)) | P15: =IFERROR(INDEX(Processos!$F$8:$F$17,MATCH(C15,Processos!$A$8:$A$17,0)),1) -> 1.017 | Q15: =IFERROR(INDEX(Matriz!$C$28:$C$33,MATCH(G15,Matriz!$A$28:$A$33,0)),0) -> 0 | R15: =IF(O15="","",ROUND(O15*P15+Q15,2)) | S15: =IF(R15="","",IF(R15>=Matriz!$C$19,4,IF(R15>=Matriz!$C$18,3,IF(R15>=Matriz!$C$17,2,1)))) | T15: =IF(S15="","",MAX(S15,IF(I15=5,Matriz!$C$23,0),IF(N15="Sim",Matriz!$C$24,0))) | U15: =IF(T15="","",CHOOSE(T15,"Baixa","Normal","Alta","Urgente")) | V15: =IF(T15="","",T15*1000+R15*10-IF(H15="",3,H15)/10-ROW()/1000000) | W15: =IF(V15="","",COUNTIF($V$5:$V$405,">"&V15)+1)
A16: 17tpepcep33 | B16: Implantar formalização de contratação com as imobiliárias selecionadas/Correspondentes (Contrato de Parceiria - Foco LGPD) | C16: Comercial Gadens | D16: Edgard Machado Ferreira Junior | E16: em progresso | F16: 46387 | G16: Definição ou decisão | O16: =IF(COUNT(I16:M16)<5,"",ROUND((I16*Matriz!$C$5+J16*Matriz!$C$6+K16*Matriz!$C$7+L16*Matriz!$C$8+M16*Matriz!$C$9)/SUM(Matriz!$C$5:$C$9),2)) | P16: =IFERROR(INDEX(Processos!$F$8:$F$17,MATCH(C16,Processos!$A$8:$A$17,0)),1) -> 1.017 | Q16: =IFERROR(INDEX(Matriz!$C$28:$C$33,MATCH(G16,Matriz!$A$28:$A$33,0)),0) -> 0 | R16: =IF(O16="","",ROUND(O16*P16+Q16,2)) | S16: =IF(R16="","",IF(R16>=Matriz!$C$19,4,IF(R16>=Matriz!$C$18,3,IF(R16>=Matriz!$C$17,2,1)))) | T16: =IF(S16="","",MAX(S16,IF(I16=5,Matriz!$C$23,0),IF(N16="Sim",Matriz!$C$24,0))) | U16: =IF(T16="","",CHOOSE(T16,"Baixa","Normal","Alta","Urgente")) | V16: =IF(T16="","",T16*1000+R16*10-IF(H16="",3,H16)/10-ROW()/1000000) | W16: =IF(V16="","",COUNTIF($V$5:$V$405,">"&V16)+1)
... A20: 17tpepcdg1v | B20: Vistoriar todas as unidades de estoque - Alessandro com apoio da AT, Comercial e Incorporação | C20: Comercial Gadens | D20: Alessandro Braz | E20: em progresso | F20: 46356 | G20: Definição ou decisão | O20: =IF(COUNT(I20:M20)<5,"",ROUND((I20*Matriz!$C$5+J20*Matriz!$C$6+K20*Matriz!$C$7+L20*Matriz!$C$8+M20*Matriz!$C$9)/SUM(Matriz!$C$5:$C$9),2)) | P20: =IFERROR(INDEX(Processos!$F$8:$F$17,MATCH(C20,Processos!$A$8:$A$17,0)),1) -> 1.017 | Q20: =IFERROR(INDEX(Matriz!$C$28:$C$33,MATCH(G20,Matriz!$A$28:$A$33,0)),0) -> 0 | R20: =IF(O20="","",ROUND(O20*P20+Q20,2)) | S20: =IF(R20="","",IF(R20>=Matriz!$C$19,4,IF(R20>=Matriz!$C$18,3,IF(R20>=Matriz!$C$17,2,1)))) | T20: =IF(S20="","",MAX(S20,IF(I20=5,Matriz!$C$23,0),IF(N20="Sim",Matriz!$C$24,0))) | U20: =IF(T20="","",CHOOSE(T20,"Baixa","Normal","Alta","Urgente")) | V20: =IF(T20="","",T20*1000+R20*10-IF(H20="",3,H20)/10-ROW()/1000000) | W20: =IF(V20="","",COUNTIF($V$5:$V$405,">"&V20)+1)
A21: 17tpepcpr2a | B21: Adequar fluxo do ClickUp de abertura de SPEs para incluir quais estão disponíveis para NN | C21: Comercial Gadens | D21: Edgard Machado Ferreira Junior | E21: sem prazo definido | G21: Definição ou decisão | O21: =IF(COUNT(I21:M21)<5,"",ROUND((I21*Matriz!$C$5+J21*Matriz!$C$6+K21*Matriz!$C$7+L21*Matriz!$C$8+M21*Matriz!$C$9)/SUM(Matriz!$C$5:$C$9),2)) | P21: =IFERROR(INDEX(Processos!$F$8:$F$17,MATCH(C21,Processos!$A$8:$A$17,0)),1) -> 1.017 | Q21: =IFERROR(INDEX(Matriz!$C$28:$C$33,MATCH(G21,Matriz!$A$28:$A$33,0)),0) -> 0 | R21: =IF(O21="","",ROUND(O21*P21+Q21,2)) | S21: =IF(R21="","",IF(R21>=Matriz!$C$19,4,IF(R21>=Matriz!$C$18,3,IF(R21>=Matriz!$C$17,2,1)))) | T21: =IF(S21="","",MAX(S21,IF(I21=5,Matriz!$C$23,0),IF(N21="Sim",Matriz!$C$24,0))) | U21: =IF(T21="","",CHOOSE(T21,"Baixa","Normal","Alta","Urgente")) | V21: =IF(T21="","",T21*1000+R21*10-IF(H21="",3,H21)/10-ROW()/1000000) | W21: =IF(V21="","",COUNTIF($V$5:$V$405,">"&V21)+1)
A22: 17tpepcgkn9 | B22: Automatizar baixa da reserva no CV | C22: Comercial Gadens | D22: Alexandre Marchiori Cruz | E22: sem prazo definido | G22: Automação ou sistema | O22: =IF(COUNT(I22:M22)<5,"",ROUND((I22*Matriz!$C$5+J22*Matriz!$C$6+K22*Matriz!$C$7+L22*Matriz!$C$8+M22*Matriz!$C$9)/SUM(Matriz!$C$5:$C$9),2)) | P22: =IFERROR(INDEX(Processos!$F$8:$F$17,MATCH(C22,Processos!$A$8:$A$17,0)),1) -> 1.017 | Q22: =IFERROR(INDEX(Matriz!$C$28:$C$33,MATCH(G22,Matriz!$A$28:$A$33,0)),0) -> 0 | R22: =IF(O22="","",ROUND(O22*P22+Q22,2)) | S22: =IF(R22="","",IF(R22>=Matriz!$C$19,4,IF(R22>=Matriz!$C$18,3,IF(R22>=Matriz!$C$17,2,1)))) | T22: =IF(S22="","",MAX(S22,IF(I22=5,Matriz!$C$23,0),IF(N22="Sim",Matriz!$C$24,0))) | U22: =IF(T22="","",CHOOSE(T22,"Baixa","Normal","Alta","Urgente")) | V22: =IF(T22="","",T22*1000+R22*10-IF(H22="",3,H22)/10-ROW()/1000000) | W22: =IF(V22="","",COUNTIF($V$5:$V$405,">"&V22)+1)
A23: 17tpepcgkmw | B23: Automatizar data da venda e competência do contrato | C23: Comercial Gadens | D23: Alexandre Marchiori Cruz | E23: sem prazo definido | G23: Automação ou sistema | O23: =IF(COUNT(I23:M23)<5,"",ROUND((I23*Matriz!$C$5+J23*Matriz!$C$6+K23*Matriz!$C$7+L23*Matriz!$C$8+M23*Matriz!$C$9)/SUM(Matriz!$C$5:$C$9),2)) | P23: =IFERROR(INDEX(Processos!$F$8:$F$17,MATCH(C23,Processos!$A$8:$A$17,0)),1) -> 1.017 | Q23: =IFERROR(INDEX(Matriz!$C$28:$C$33,MATCH(G23,Matriz!$A$28:$A$33,0)),0) -> 0 | R23: =IF(O23="","",ROUND(O23*P23+Q23,2)) | S23: =IF(R23="","",IF(R23>=Matriz!$C$19,4,IF(R23>=Matriz!$C$18,3,IF(R23>=Matriz!$C$17,2,1)))) | T23: =IF(S23="","",MAX(S23,IF(I23=5,Matriz!$C$23,0),IF(N23="Sim",Matriz!$C$24,0))) | U23: =IF(T23="","",CHOOSE(T23,"Baixa","Normal","Alta","Urgente")) | V23: =IF(T23="","",T23*1000+R23*10-IF(H23="",3,H23)/10-ROW()/1000000) | W23: =IF(V23="","",COUNTIF($V$5:$V$405,">"&V23)+1)
A24: 17tpepcpr27 | B24: Automatizar informação de decisão de opção de planta escolhida pelo cliente, via CV, para Planejamento e Controle | C24: Comercial Gadens | D24: Alexandre Marchiori Cruz | E24: sem prazo definido | G24: Automação ou sistema | O24: =IF(COUNT(I24:M24)<5,"",ROUND((I24*Matriz!$C$5+J24*Matriz!$C$6+K24*Matriz!$C$7+L24*Matriz!$C$8+M24*Matriz!$C$9)/SUM(Matriz!$C$5:$C$9),2)) | P24: =IFERROR(INDEX(Processos!$F$8:$F$17,MATCH(C24,Processos!$A$8:$A$17,0)),1) -> 1.017 | Q24: =IFERROR(INDEX(Matriz!$C$28:$C$33,MATCH(G24,Matriz!$A$28:$A$33,0)),0) -> 0 | R24: =IF(O24="","",ROUND(O24*P24+Q24,2)) | S24: =IF(R24="","",IF(R24>=Matriz!$C$19,4,IF(R24>=Matriz!$C$18,3,IF(R24>=Matriz!$C$17,2,1)))) | T24: =IF(S24="","",MAX(S24,IF(I24=5,Matriz!$C$23,0),IF(N24="Sim",Matriz!$C$24,0))) | U24: =IF(T24="","",CHOOSE(T24,"Baixa","Normal","Alta","Urgente")) | V24: =IF(T24="","",T24*1000+R24*10-IF(H24="",3,H24)/10-ROW()/1000000) | W24: =IF(V24="","",COUNTIF($V$5:$V$405,">"&V24)+1)
A25: 17tpepcdm2z | B25: Automatizar processo de contratação com imobiliárias selecionadas | C25: Comercial Gadens | D25: Alexandre Marchiori Cruz | E25: sem prazo definido | G25: Automação ou sistema | O25: =IF(COUNT(I25:M25)<5,"",ROUND((I25*Matriz!$C$5+J25*Matriz!$C$6+K25*Matriz!$C$7+L25*Matriz!$C$8+M25*Matriz!$C$9)/SUM(Matriz!$C$5:$C$9),2)) | P25: =IFERROR(INDEX(Processos!$F$8:$F$17,MATCH(C25,Processos!$A$8:$A$17,0)),1) -> 1.017 | Q25: =IFERROR(INDEX(Matriz!$C$28:$C$33,MATCH(G25,Matriz!$A$28:$A$33,0)),0) -> 0 | R25: =IF(O25="","",ROUND(O25*P25+Q25,2)) | S25: =IF(R25="","",IF(R25>=Matriz!$C$19,4,IF(R25>=Matriz!$C$18,3,IF(R25>=Matriz!$C$17,2,1)))) | T25: =IF(S25="","",MAX(S25,IF(I25=5,Matriz!$C$23,0),IF(N25="Sim",Matriz!$C$24,0))) | U25: =IF(T25="","",CHOOSE(T25,"Baixa","Normal","Alta","Urgente")) | V25: =IF(T25="","",T25*1000+R25*10-IF(H25="",3,H25)/10-ROW()/1000000) | W25: =IF(V25="","",COUNTIF($V$5:$V$405,">"&V25)+1)
A26: 17tpepcdaee | B26: Avaliar automatização do processo de leads - WhatsApp vs CV Gadens | C26: Comercial Gadens | D26: Alexandre Marchiori Cruz | E26: sem prazo definido | G26: Automação ou sistema | O26: =IF(COUNT(I26:M26)<5,"",ROUND((I26*Matriz!$C$5+J26*Matriz!$C$6+K26*Matriz!$C$7+L26*Matriz!$C$8+M26*Matriz!$C$9)/SUM(Matriz!$C$5:$C$9),2)) | P26: =IFERROR(INDEX(Processos!$F$8:$F$17,MATCH(C26,Processos!$A$8:$A$17,0)),1) -> 1.017 | Q26: =IFERROR(INDEX(Matriz!$C$28:$C$33,MATCH(G26,Matriz!$A$28:$A$33,0)),0) -> 0 | R26: =IF(O26="","",ROUND(O26*P26+Q26,2)) | S26: =IF(R26="","",IF(R26>=Matriz!$C$19,4,IF(R26>=Matriz!$C$18,3,IF(R26>=Matriz!$C$17,2,1)))) | T26: =IF(S26="","",MAX(S26,IF(I26=5,Matriz!$C$23,0),IF(N26="Sim",Matriz!$C$24,0))) | U26: =IF(T26="","",CHOOSE(T26,"Baixa","Normal","Alta","Urgente")) | V26: =IF(T26="","",T26*1000+R26*10-IF(H26="",3,H26)/10-ROW()/1000000) | W26: =IF(V26="","",COUNTIF($V$5:$V$405,">"&V26)+1)
A27: 17tpepcpr2y | B27: Avaliar bloqueio de unidades permutadas dentro do Mega a partir do CV | C27: Comercial Gadens | D27: Alexandre Marchiori Cruz | E27: sem prazo definido | G27: Controle | O27: =IF(COUNT(I27:M27)<5,"",ROUND((I27*Matriz!$C$5+J27*Matriz!$C$6+K27*Matriz!$C$7+L27*Matriz!$C$8+M27*Matriz!$C$9)/SUM(Matriz!$C$5:$C$9),2)) | P27: =IFERROR(INDEX(Processos!$F$8:$F$17,MATCH(C27,Processos!$A$8:$A$17,0)),1) -> 1.017 | Q27: =IFERROR(INDEX(Matriz!$C$28:$C$33,MATCH(G27,Matriz!$A$28:$A$33,0)),0) -> 0.3 | R27: =IF(O27="","",ROUND(O27*P27+Q27,2)) | S27: =IF(R27="","",IF(R27>=Matriz!$C$19,4,IF(R27>=Matriz!$C$18,3,IF(R27>=Matriz!$C$17,2,1)))) | T27: =IF(S27="","",MAX(S27,IF(I27=5,Matriz!$C$23,0),IF(N27="Sim",Matriz!$C$24,0))) | U27: =IF(T27="","",CHOOSE(T27,"Baixa","Normal","Alta","Urgente")) | V27: =IF(T27="","",T27*1000+R27*10-IF(H27="",3,H27)/10-ROW()/1000000) | W27: =IF(V27="","",COUNTIF($V$5:$V$405,">"&V27)+1)
A28: 17tpepcpr26 | B28: Avaliar com as construtoras prazo máximo para alteração de opção de planta | C28: Comercial Gadens | D28: Hellen Venturoso | E28: sem prazo definido | G28: Definição ou decisão | O28: =IF(COUNT(I28:M28)<5,"",ROUND((I28*Matriz!$C$5+J28*Matriz!$C$6+K28*Matriz!$C$7+L28*Matriz!$C$8+M28*Matriz!$C$9)/SUM(Matriz!$C$5:$C$9),2)) | P28: =IFERROR(INDEX(Processos!$F$8:$F$17,MATCH(C28,Processos!$A$8:$A$17,0)),1) -> 1.017 | Q28: =IFERROR(INDEX(Matriz!$C$28:$C$33,MATCH(G28,Matriz!$A$28:$A$33,0)),0) -> 0 | R28: =IF(O28="","",ROUND(O28*P28+Q28,2)) | S28: =IF(R28="","",IF(R28>=Matriz!$C$19,4,IF(R28>=Matriz!$C$18,3,IF(R28>=Matriz!$C$17,2,1)))) | T28: =IF(S28="","",MAX(S28,IF(I28=5,Matriz!$C$23,0),IF(N28="Sim",Matriz!$C$24,0))) | U28: =IF(T28="","",CHOOSE(T28,"Baixa","Normal","Alta","Urgente")) | V28: =IF(T28="","",T28*1000+R28*10-IF(H28="",3,H28)/10-ROW()/1000000) | W28: =IF(V28="","",COUNTIF($V$5:$V$405,">"&V28)+1)
A29: 17tpepcgqnr | B29: Avaliar impacto da reforma tributária na migração de pessoa física para pessoa jurídica | C29: Comercial Gadens | D29: Érica Ferreira Tavares Silva Caldeira, Paulo Tavares | E29: sem prazo definido | G29: Definição ou decisão | O29: =IF(COUNT(I29:M29)<5,"",ROUND((I29*Matriz!$C$5+J29*Matriz!$C$6+K29*Matriz!$C$7+L29*Matriz!$C$8+M29*Matriz!$C$9)/SUM(Matriz!$C$5:$C$9),2)) | P29: =IFERROR(INDEX(Processos!$F$8:$F$17,MATCH(C29,Processos!$A$8:$A$17,0)),1) -> 1.017 | Q29: =IFERROR(INDEX(Matriz!$C$28:$C$33,MATCH(G29,Matriz!$A$28:$A$33,0)),0) -> 0 | R29: =IF(O29="","",ROUND(O29*P29+Q29,2)) | S29: =IF(R29="","",IF(R29>=Matriz!$C$19,4,IF(R29>=Matriz!$C$18,3,IF(R29>=Matriz!$C$17,2,1)))) | T29: =IF(S29="","",MAX(S29,IF(I29=5,Matriz!$C$23,0),IF(N29="Sim",Matriz!$C$24,0))) | U29: =IF(T29="","",CHOOSE(T29,"Baixa","Normal","Alta","Urgente")) | V29: =IF(T29="","",T29*1000+R29*10-IF(H29="",3,H29)/10-ROW()/1000000) | W29: =IF(V29="","",COUNTIF($V$5:$V$405,">"&V29)+1)
A30: 17tpepcpr2q | B30: Avaliar informação automática sobre cadastro do contrato de permuta financeira, através do Mega Inteligence, ou solução similar | C30: Comercial Gadens | D30: Alexandre Marchiori Cruz | E30: sem prazo definido | G30: Automação ou sistema | O30: =IF(COUNT(I30:M30)<5,"",ROUND((I30*Matriz!$C$5+J30*Matriz!$C$6+K30*Matriz!$C$7+L30*Matriz!$C$8+M30*Matriz!$C$9)/SUM(Matriz!$C$5:$C$9),2)) | P30: =IFERROR(INDEX(Processos!$F$8:$F$17,MATCH(C30,Processos!$A$8:$A$17,0)),1) -> 1.017 | Q30: =IFERROR(INDEX(Matriz!$C$28:$C$33,MATCH(G30,Matriz!$A$28:$A$33,0)),0) -> 0 | R30: =IF(O30="","",ROUND(O30*P30+Q30,2)) | S30: =IF(R30="","",IF(R30>=Matriz!$C$19,4,IF(R30>=Matriz!$C$18,3,IF(R30>=Matriz!$C$17,2,1)))) | T30: =IF(S30="","",MAX(S30,IF(I30=5,Matriz!$C$23,0),IF(N30="Sim",Matriz!$C$24,0))) | U30: =IF(T30="","",CHOOSE(T30,"Baixa","Normal","Alta","Urgente")) | V30: =IF(T30="","",T30*1000+R30*10-IF(H30="",3,H30)/10-ROW()/1000000) | W30: =IF(V30="","",COUNTIF($V$5:$V$405,">"&V30)+1)
A31: 17tpepcpr2c | B31: Avaliar padronização de nomenclatura das permutas / justificativas de bloqueio no CV (Make It e Gadens) | C31: Comercial Gadens | D31: André Garcia Vilas Boas, Mônica Massaneiro | E31: sem prazo definido | G31: Controle | O31: =IF(COUNT(I31:M31)<5,"",ROUND((I31*Matriz!$C$5+J31*Matriz!$C$6+K31*Matriz!$C$7+L31*Matriz!$C$8+M31*Matriz!$C$9)/SUM(Matriz!$C$5:$C$9),2)) | P31: =IFERROR(INDEX(Processos!$F$8:$F$17,MATCH(C31,Processos!$A$8:$A$17,0)),1) -> 1.017 | Q31: =IFERROR(INDEX(Matriz!$C$28:$C$33,MATCH(G31,Matriz!$A$28:$A$33,0)),0) -> 0.3 | R31: =IF(O31="","",ROUND(O31*P31+Q31,2)) | S31: =IF(R31="","",IF(R31>=Matriz!$C$19,4,IF(R31>=Matriz!$C$18,3,IF(R31>=Matriz!$C$17,2,1)))) | T31: =IF(S31="","",MAX(S31,IF(I31=5,Matriz!$C$23,0),IF(N31="Sim",Matriz!$C$24,0))) | U31: =IF(T31="","",CHOOSE(T31,"Baixa","Normal","Alta","Urgente")) | V31: =IF(T31="","",T31*1000+R31*10-IF(H31="",3,H31)/10-ROW()/1000000) | W31: =IF(V31="","",COUNTIF($V$5:$V$405,">"&V31)+1)
A32: 17tpepcdm2y | B32: Avaliar plataforma para registro de campanhas exclusivas (hoje efetuado no Sharepoint) | C32: Comercial Gadens | D32: Alexandre Marchiori Cruz | E32: sem prazo definido | G32: Automação ou sistema | O32: =IF(COUNT(I32:M32)<5,"",ROUND((I32*Matriz!$C$5+J32*Matriz!$C$6+K32*Matriz!$C$7+L32*Matriz!$C$8+M32*Matriz!$C$9)/SUM(Matriz!$C$5:$C$9),2)) | P32: =IFERROR(INDEX(Processos!$F$8:$F$17,MATCH(C32,Processos!$A$8:$A$17,0)),1) -> 1.017 | Q32: =IFERROR(INDEX(Matriz!$C$28:$C$33,MATCH(G32,Matriz!$A$28:$A$33,0)),0) -> 0 | R32: =IF(O32="","",ROUND(O32*P32+Q32,2)) | S32: =IF(R32="","",IF(R32>=Matriz!$C$19,4,IF(R32>=Matriz!$C$18,3,IF(R32>=Matriz!$C$17,2,1)))) | T32: =IF(S32="","",MAX(S32,IF(I32=5,Matriz!$C$23,0),IF(N32="Sim",Matriz!$C$24,0))) | U32: =IF(T32="","",CHOOSE(T32,"Baixa","Normal","Alta","Urgente")) | V32: =IF(T32="","",T32*1000+R32*10-IF(H32="",3,H32)/10-ROW()/1000000) | W32: =IF(V32="","",COUNTIF($V$5:$V$405,">"&V32)+1)
... A34: 17tpepcenxf | B34: Avaliar trava no CV sobre comissão dos contratos vendidos por modalidade - Gadens | C34: Comercial Gadens | D34: Alexandre Marchiori Cruz | E34: sem prazo definido | G34: Controle | O34: =IF(COUNT(I34:M34)<5,"",ROUND((I34*Matriz!$C$5+J34*Matriz!$C$6+K34*Matriz!$C$7+L34*Matriz!$C$8+M34*Matriz!$C$9)/SUM(Matriz!$C$5:$C$9),2)) | P34: =IFERROR(INDEX(Processos!$F$8:$F$17,MATCH(C34,Processos!$A$8:$A$17,0)),1) -> 1.017 | Q34: =IFERROR(INDEX(Matriz!$C$28:$C$33,MATCH(G34,Matriz!$A$28:$A$33,0)),0) -> 0.3 | R34: =IF(O34="","",ROUND(O34*P34+Q34,2)) | S34: =IF(R34="","",IF(R34>=Matriz!$C$19,4,IF(R34>=Matriz!$C$18,3,IF(R34>=Matriz!$C$17,2,1)))) | T34: =IF(S34="","",MAX(S34,IF(I34=5,Matriz!$C$23,0),IF(N34="Sim",Matriz!$C$24,0))) | U34: =IF(T34="","",CHOOSE(T34,"Baixa","Normal","Alta","Urgente")) | V34: =IF(T34="","",T34*1000+R34*10-IF(H34="",3,H34)/10-ROW()/1000000) | W34: =IF(V34="","",COUNTIF($V$5:$V$405,">"&V34)+1)
A35: 17tpepcgkv5 | B35: Avaliar venda via consórcio | C35: Comercial Gadens | D35: Marcelo Renato Nascimento Cerqueira | E35: sem prazo definido | G35: Definição ou decisão | H35: 3 | I35: 2 | J35: 3 | K35: 1 | L35: 3 | M35: 1 | N35: Não | O35: =IF(COUNT(I35:M35)<5,"",ROUND((I35*Matriz!$C$5+J35*Matriz!$C$6+K35*Matriz!$C$7+L35*Matriz!$C$8+M35*Matriz!$C$9)/SUM(Matriz!$C$5:$C$9),2)) -> 2 | P35: =IFERROR(INDEX(Processos!$F$8:$F$17,MATCH(C35,Processos!$A$8:$A$17,0)),1) -> 1.017 | Q35: =IFERROR(INDEX(Matriz!$C$28:$C$33,MATCH(G35,Matriz!$A$28:$A$33,0)),0) -> 0 | R35: =IF(O35="","",ROUND(O35*P35+Q35,2)) -> 2.03 | S35: =IF(R35="","",IF(R35>=Matriz!$C$19,4,IF(R35>=Matriz!$C$18,3,IF(R35>=Matriz!$C$17,2,1)))) -> 1 | T35: =IF(S35="","",MAX(S35,IF(I35=5,Matriz!$C$23,0),IF(N35="Sim",Matriz!$C$24,0))) -> 1 | U35: =IF(T35="","",CHOOSE(T35,"Baixa","Normal","Alta","Urgente")) -> Baixa | V35: =IF(T35="","",T35*1000+R35*10-IF(H35="",3,H35)/10-ROW()/1000000) -> 1020 | W35: =IF(V35="","",COUNTIF($V$5:$V$405,">"&V35)+1) -> 11 | X35: Âncora (proposta) | Y35: Avaliar uma modalidade nova de venda: decisão, sem risco imediato.
A36: 17tpepcpr2b | B36: Avaliar viabilidade de continuar SPE distratada ou necessidade de uma nova abertura | C36: Comercial Gadens | D36: Paulo Tavares | E36: sem prazo definido | G36: Definição ou decisão | O36: =IF(COUNT(I36:M36)<5,"",ROUND((I36*Matriz!$C$5+J36*Matriz!$C$6+K36*Matriz!$C$7+L36*Matriz!$C$8+M36*Matriz!$C$9)/SUM(Matriz!$C$5:$C$9),2)) | P36: =IFERROR(INDEX(Processos!$F$8:$F$17,MATCH(C36,Processos!$A$8:$A$17,0)),1) -> 1.017 | Q36: =IFERROR(INDEX(Matriz!$C$28:$C$33,MATCH(G36,Matriz!$A$28:$A$33,0)),0) -> 0 | R36: =IF(O36="","",ROUND(O36*P36+Q36,2)) | S36: =IF(R36="","",IF(R36>=Matriz!$C$19,4,IF(R36>=Matriz!$C$18,3,IF(R36>=Matriz!$C$17,2,1)))) | T36: =IF(S36="","",MAX(S36,IF(I36=5,Matriz!$C$23,0),IF(N36="Sim",Matriz!$C$24,0))) | U36: =IF(T36="","",CHOOSE(T36,"Baixa","Normal","Alta","Urgente")) | V36: =IF(T36="","",T36*1000+R36*10-IF(H36="",3,H36)/10-ROW()/1000000) | W36: =IF(V36="","",COUNTIF($V$5:$V$405,">"&V36)+1)
A37: 17tpepcpr24 | B37: Criar campo no CV para permutante e tipos de permuta | C37: Comercial Gadens | D37: Alexandre Marchiori Cruz | E37: sem prazo definido | G37: Automação ou sistema | H37: 2 | I37: 3 | J37: 3 | K37: 1 | L37: 2 | M37: 4 | N37: Não | O37: =IF(COUNT(I37:M37)<5,"",ROUND((I37*Matriz!$C$5+J37*Matriz!$C$6+K37*Matriz!$C$7+L37*Matriz!$C$8+M37*Matriz!$C$9)/SUM(Matriz!$C$5:$C$9),2)) -> 2.6 | P37: =IFERROR(INDEX(Processos!$F$8:$F$17,MATCH(C37,Processos!$A$8:$A$17,0)),1) -> 1.017 | Q37: =IFERROR(INDEX(Matriz!$C$28:$C$33,MATCH(G37,Matriz!$A$28:$A$33,0)),0) -> 0 | R37: =IF(O37="","",ROUND(O37*P37+Q37,2)) -> 2.64 | S37: =IF(R37="","",IF(R37>=Matriz!$C$19,4,IF(R37>=Matriz!$C$18,3,IF(R37>=Matriz!$C$17,2,1)))) -> 2 | T37: =IF(S37="","",MAX(S37,IF(I37=5,Matriz!$C$23,0),IF(N37="Sim",Matriz!$C$24,0))) -> 2 | U37: =IF(T37="","",CHOOSE(T37,"Baixa","Normal","Alta","Urgente")) -> Normal | V37: =IF(T37="","",T37*1000+R37*10-IF(H37="",3,H37)/10-ROW()/1000000) -> 2026.2 | W37: =IF(V37="","",COUNTIF($V$5:$V$405,">"&V37)+1) -> 10 | X37: Âncora (proposta) | Y37: Campo de permutante e tipos de permuta no CV: vários fluxos de permuta dependem dele.
A38: 17tpepcdg1x | B38: Criar lista de fornecedores para base - Sergio apoio Mariane; | C38: Comercial Gadens | D38: Sergio Lopes | E38: sem prazo definido | G38: Definição ou decisão | O38: =IF(COUNT(I38:M38)<5,"",ROUND((I38*Matriz!$C$5+J38*Matriz!$C$6+K38*Matriz!$C$7+L38*Matriz!$C$8+M38*Matriz!$C$9)/SUM(Matriz!$C$5:$C$9),2)) | P38: =IFERROR(INDEX(Processos!$F$8:$F$17,MATCH(C38,Processos!$A$8:$A$17,0)),1) -> 1.017 | Q38: =IFERROR(INDEX(Matriz!$C$28:$C$33,MATCH(G38,Matriz!$A$28:$A$33,0)),0) -> 0 | R38: =IF(O38="","",ROUND(O38*P38+Q38,2)) | S38: =IF(R38="","",IF(R38>=Matriz!$C$19,4,IF(R38>=Matriz!$C$18,3,IF(R38>=Matriz!$C$17,2,1)))) | T38: =IF(S38="","",MAX(S38,IF(I38=5,Matriz!$C$23,0),IF(N38="Sim",Matriz!$C$24,0))) | U38: =IF(T38="","",CHOOSE(T38,"Baixa","Normal","Alta","Urgente")) | V38: =IF(T38="","",T38*1000+R38*10-IF(H38="",3,H38)/10-ROW()/1000000) | W38: =IF(V38="","",COUNTIF($V$5:$V$405,">"&V38)+1)
A39: 17tpepcdg20 | B39: Definir centro de custo e verba de manutenção de estoque | C39: Comercial Gadens | D39: Mônica Massaneiro | E39: sem prazo definido | G39: Definição ou decisão | O39: =IF(COUNT(I39:M39)<5,"",ROUND((I39*Matriz!$C$5+J39*Matriz!$C$6+K39*Matriz!$C$7+L39*Matriz!$C$8+M39*Matriz!$C$9)/SUM(Matriz!$C$5:$C$9),2)) | P39: =IFERROR(INDEX(Processos!$F$8:$F$17,MATCH(C39,Processos!$A$8:$A$17,0)),1) -> 1.017 | Q39: =IFERROR(INDEX(Matriz!$C$28:$C$33,MATCH(G39,Matriz!$A$28:$A$33,0)),0) -> 0 | R39: =IF(O39="","",ROUND(O39*P39+Q39,2)) | S39: =IF(R39="","",IF(R39>=Matriz!$C$19,4,IF(R39>=Matriz!$C$18,3,IF(R39>=Matriz!$C$17,2,1)))) | T39: =IF(S39="","",MAX(S39,IF(I39=5,Matriz!$C$23,0),IF(N39="Sim",Matriz!$C$24,0))) | U39: =IF(T39="","",CHOOSE(T39,"Baixa","Normal","Alta","Urgente")) | V39: =IF(T39="","",T39*1000+R39*10-IF(H39="",3,H39)/10-ROW()/1000000) | W39: =IF(V39="","",COUNTIF($V$5:$V$405,">"&V39)+1)
A40: 17tpepcgqnq | B40: Definir critérios da venda direta | C40: Comercial Gadens | D40: Érica Ferreira Tavares Silva Caldeira | E40: sem prazo definido | G40: Definição ou decisão | O40: =IF(COUNT(I40:M40)<5,"",ROUND((I40*Matriz!$C$5+J40*Matriz!$C$6+K40*Matriz!$C$7+L40*Matriz!$C$8+M40*Matriz!$C$9)/SUM(Matriz!$C$5:$C$9),2)) | P40: =IFERROR(INDEX(Processos!$F$8:$F$17,MATCH(C40,Processos!$A$8:$A$17,0)),1) -> 1.017 | Q40: =IFERROR(INDEX(Matriz!$C$28:$C$33,MATCH(G40,Matriz!$A$28:$A$33,0)),0) -> 0 | R40: =IF(O40="","",ROUND(O40*P40+Q40,2)) | S40: =IF(R40="","",IF(R40>=Matriz!$C$19,4,IF(R40>=Matriz!$C$18,3,IF(R40>=Matriz!$C$17,2,1)))) | T40: =IF(S40="","",MAX(S40,IF(I40=5,Matriz!$C$23,0),IF(N40="Sim",Matriz!$C$24,0))) | U40: =IF(T40="","",CHOOSE(T40,"Baixa","Normal","Alta","Urgente")) | V40: =IF(T40="","",T40*1000+R40*10-IF(H40="",3,H40)/10-ROW()/1000000) | W40: =IF(V40="","",COUNTIF($V$5:$V$405,">"&V40)+1)
A41: 17tpepcdm33 | B41: Definir fluxo de contratos personalizados no CV e treinar os envolvidos - Gadens | C41: Comercial Gadens | D41: Alexandre Marchiori Cruz | E41: sem prazo definido | G41: Treinamento | O41: =IF(COUNT(I41:M41)<5,"",ROUND((I41*Matriz!$C$5+J41*Matriz!$C$6+K41*Matriz!$C$7+L41*Matriz!$C$8+M41*Matriz!$C$9)/SUM(Matriz!$C$5:$C$9),2)) | P41: =IFERROR(INDEX(Processos!$F$8:$F$17,MATCH(C41,Processos!$A$8:$A$17,0)),1) -> 1.017 | Q41: =IFERROR(INDEX(Matriz!$C$28:$C$33,MATCH(G41,Matriz!$A$28:$A$33,0)),0) -> -0.2 | R41: =IF(O41="","",ROUND(O41*P41+Q41,2)) | S41: =IF(R41="","",IF(R41>=Matriz!$C$19,4,IF(R41>=Matriz!$C$18,3,IF(R41>=Matriz!$C$17,2,1)))) | T41: =IF(S41="","",MAX(S41,IF(I41=5,Matriz!$C$23,0),IF(N41="Sim",Matriz!$C$24,0))) | U41: =IF(T41="","",CHOOSE(T41,"Baixa","Normal","Alta","Urgente")) | V41: =IF(T41="","",T41*1000+R41*10-IF(H41="",3,H41)/10-ROW()/1000000) | W41: =IF(V41="","",COUNTIF($V$5:$V$405,">"&V41)+1)
A42: 17tpepcpr2m | B42: Definir regras de comercialização das unidades pelo permutante - Make It e Gadens | C42: Comercial Gadens | D42: André Garcia Vilas Boas, Mônica Massaneiro | E42: sem prazo definido | G42: Definição ou decisão | O42: =IF(COUNT(I42:M42)<5,"",ROUND((I42*Matriz!$C$5+J42*Matriz!$C$6+K42*Matriz!$C$7+L42*Matriz!$C$8+M42*Matriz!$C$9)/SUM(Matriz!$C$5:$C$9),2)) | P42: =IFERROR(INDEX(Processos!$F$8:$F$17,MATCH(C42,Processos!$A$8:$A$17,0)),1) -> 1.017 | Q42: =IFERROR(INDEX(Matriz!$C$28:$C$33,MATCH(G42,Matriz!$A$28:$A$33,0)),0) -> 0 | R42: =IF(O42="","",ROUND(O42*P42+Q42,2)) | S42: =IF(R42="","",IF(R42>=Matriz!$C$19,4,IF(R42>=Matriz!$C$18,3,IF(R42>=Matriz!$C$17,2,1)))) | T42: =IF(S42="","",MAX(S42,IF(I42=5,Matriz!$C$23,0),IF(N42="Sim",Matriz!$C$24,0))) | U42: =IF(T42="","",CHOOSE(T42,"Baixa","Normal","Alta","Urgente")) | V42: =IF(T42="","",T42*1000+R42*10-IF(H42="",3,H42)/10-ROW()/1000000) | W42: =IF(V42="","",COUNTIF($V$5:$V$405,">"&V42)+1)
A43: 17tpepcdk0p | B43: Elaborar POP - Critérios de seleção de correspondentes | C43: Comercial Gadens | D43: Mônica Massaneiro | E43: sem prazo definido | G43: Documento normativo | O43: =IF(COUNT(I43:M43)<5,"",ROUND((I43*Matriz!$C$5+J43*Matriz!$C$6+K43*Matriz!$C$7+L43*Matriz!$C$8+M43*Matriz!$C$9)/SUM(Matriz!$C$5:$C$9),2)) | P43: =IFERROR(INDEX(Processos!$F$8:$F$17,MATCH(C43,Processos!$A$8:$A$17,0)),1) -> 1.017 | Q43: =IFERROR(INDEX(Matriz!$C$28:$C$33,MATCH(G43,Matriz!$A$28:$A$33,0)),0) -> 0 | R43: =IF(O43="","",ROUND(O43*P43+Q43,2)) | S43: =IF(R43="","",IF(R43>=Matriz!$C$19,4,IF(R43>=Matriz!$C$18,3,IF(R43>=Matriz!$C$17,2,1)))) | T43: =IF(S43="","",MAX(S43,IF(I43=5,Matriz!$C$23,0),IF(N43="Sim",Matriz!$C$24,0))) | U43: =IF(T43="","",CHOOSE(T43,"Baixa","Normal","Alta","Urgente")) | V43: =IF(T43="","",T43*1000+R43*10-IF(H43="",3,H43)/10-ROW()/1000000) | W43: =IF(V43="","",COUNTIF($V$5:$V$405,">"&V43)+1)
A44: 17tpepcdm30 | B44: Encerramento automático de contrato em caso de não pagamento de sinal | C44: Comercial Gadens | D44: Alexandre Marchiori Cruz | E44: sem prazo definido | G44: Definição ou decisão | O44: =IF(COUNT(I44:M44)<5,"",ROUND((I44*Matriz!$C$5+J44*Matriz!$C$6+K44*Matriz!$C$7+L44*Matriz!$C$8+M44*Matriz!$C$9)/SUM(Matriz!$C$5:$C$9),2)) | P44: =IFERROR(INDEX(Processos!$F$8:$F$17,MATCH(C44,Processos!$A$8:$A$17,0)),1) -> 1.017 | Q44: =IFERROR(INDEX(Matriz!$C$28:$C$33,MATCH(G44,Matriz!$A$28:$A$33,0)),0) -> 0 | R44: =IF(O44="","",ROUND(O44*P44+Q44,2)) | S44: =IF(R44="","",IF(R44>=Matriz!$C$19,4,IF(R44>=Matriz!$C$18,3,IF(R44>=Matriz!$C$17,2,1)))) | T44: =IF(S44="","",MAX(S44,IF(I44=5,Matriz!$C$23,0),IF(N44="Sim",Matriz!$C$24,0))) | U44: =IF(T44="","",CHOOSE(T44,"Baixa","Normal","Alta","Urgente")) | V44: =IF(T44="","",T44*1000+R44*10-IF(H44="",3,H44)/10-ROW()/1000000) | W44: =IF(V44="","",COUNTIF($V$5:$V$405,">"&V44)+1)
A45: 17tpepcdm32 | B45: Fluxo de proposta via CV | C45: Comercial Gadens | D45: Alexandre Marchiori Cruz | E45: sem prazo definido | G45: Automação ou sistema | O45: =IF(COUNT(I45:M45)<5,"",ROUND((I45*Matriz!$C$5+J45*Matriz!$C$6+K45*Matriz!$C$7+L45*Matriz!$C$8+M45*Matriz!$C$9)/SUM(Matriz!$C$5:$C$9),2)) | P45: =IFERROR(INDEX(Processos!$F$8:$F$17,MATCH(C45,Processos!$A$8:$A$17,0)),1) -> 1.017 | Q45: =IFERROR(INDEX(Matriz!$C$28:$C$33,MATCH(G45,Matriz!$A$28:$A$33,0)),0) -> 0 | R45: =IF(O45="","",ROUND(O45*P45+Q45,2)) | S45: =IF(R45="","",IF(R45>=Matriz!$C$19,4,IF(R45>=Matriz!$C$18,3,IF(R45>=Matriz!$C$17,2,1)))) | T45: =IF(S45="","",MAX(S45,IF(I45=5,Matriz!$C$23,0),IF(N45="Sim",Matriz!$C$24,0))) | U45: =IF(T45="","",CHOOSE(T45,"Baixa","Normal","Alta","Urgente")) | V45: =IF(T45="","",T45*1000+R45*10-IF(H45="",3,H45)/10-ROW()/1000000) | W45: =IF(V45="","",COUNTIF($V$5:$V$405,">"&V45)+1)
A46: 17tpepcpr29 | B46: Formalizar envolvidos que não será mais permitido a personalização de unidades | C46: Comercial Gadens | D46: Mariane Cristine Machado Scandelari | E46: sem prazo definido | G46: Definição ou decisão | O46: =IF(COUNT(I46:M46)<5,"",ROUND((I46*Matriz!$C$5+J46*Matriz!$C$6+K46*Matriz!$C$7+L46*Matriz!$C$8+M46*Matriz!$C$9)/SUM(Matriz!$C$5:$C$9),2)) | P46: =IFERROR(INDEX(Processos!$F$8:$F$17,MATCH(C46,Processos!$A$8:$A$17,0)),1) -> 1.017 | Q46: =IFERROR(INDEX(Matriz!$C$28:$C$33,MATCH(G46,Matriz!$A$28:$A$33,0)),0) -> 0 | R46: =IF(O46="","",ROUND(O46*P46+Q46,2)) | S46: =IF(R46="","",IF(R46>=Matriz!$C$19,4,IF(R46>=Matriz!$C$18,3,IF(R46>=Matriz!$C$17,2,1)))) | T46: =IF(S46="","",MAX(S46,IF(I46=5,Matriz!$C$23,0),IF(N46="Sim",Matriz!$C$24,0))) | U46: =IF(T46="","",CHOOSE(T46,"Baixa","Normal","Alta","Urgente")) | V46: =IF(T46="","",T46*1000+R46*10-IF(H46="",3,H46)/10-ROW()/1000000) | W46: =IF(V46="","",COUNTIF($V$5:$V$405,">"&V46)+1)
A47: 17tpepcgmj8 | B47: Formalizar regras de fechamento mensal comercial | C47: Comercial Gadens | D47: Marcelo Renato Nascimento Cerqueira | E47: sem prazo definido | G47: Definição ou decisão | O47: =IF(COUNT(I47:M47)<5,"",ROUND((I47*Matriz!$C$5+J47*Matriz!$C$6+K47*Matriz!$C$7+L47*Matriz!$C$8+M47*Matriz!$C$9)/SUM(Matriz!$C$5:$C$9),2)) | P47: =IFERROR(INDEX(Processos!$F$8:$F$17,MATCH(C47,Processos!$A$8:$A$17,0)),1) -> 1.017 | Q47: =IFERROR(INDEX(Matriz!$C$28:$C$33,MATCH(G47,Matriz!$A$28:$A$33,0)),0) -> 0 | R47: =IF(O47="","",ROUND(O47*P47+Q47,2)) | S47: =IF(R47="","",IF(R47>=Matriz!$C$19,4,IF(R47>=Matriz!$C$18,3,IF(R47>=Matriz!$C$17,2,1)))) | T47: =IF(S47="","",MAX(S47,IF(I47=5,Matriz!$C$23,0),IF(N47="Sim",Matriz!$C$24,0))) | U47: =IF(T47="","",CHOOSE(T47,"Baixa","Normal","Alta","Urgente")) | V47: =IF(T47="","",T47*1000+R47*10-IF(H47="",3,H47)/10-ROW()/1000000) | W47: =IF(V47="","",COUNTIF($V$5:$V$405,">"&V47)+1)
A48: 17tpepcpr2r | B48: Implantar cálculo do valor do repasse ao terreneiro realizado sistemicamente (Gabriel Arantes) | C48: Comercial Gadens | D48: Vanderlei Maturicio | E48: sem prazo definido | G48: Definição ou decisão | O48: =IF(COUNT(I48:M48)<5,"",ROUND((I48*Matriz!$C$5+J48*Matriz!$C$6+K48*Matriz!$C$7+L48*Matriz!$C$8+M48*Matriz!$C$9)/SUM(Matriz!$C$5:$C$9),2)) | P48: =IFERROR(INDEX(Processos!$F$8:$F$17,MATCH(C48,Processos!$A$8:$A$17,0)),1) -> 1.017 | Q48: =IFERROR(INDEX(Matriz!$C$28:$C$33,MATCH(G48,Matriz!$A$28:$A$33,0)),0) -> 0 | R48: =IF(O48="","",ROUND(O48*P48+Q48,2)) | S48: =IF(R48="","",IF(R48>=Matriz!$C$19,4,IF(R48>=Matriz!$C$18,3,IF(R48>=Matriz!$C$17,2,1)))) | T48: =IF(S48="","",MAX(S48,IF(I48=5,Matriz!$C$23,0),IF(N48="Sim",Matriz!$C$24,0))) | U48: =IF(T48="","",CHOOSE(T48,"Baixa","Normal","Alta","Urgente")) | V48: =IF(T48="","",T48*1000+R48*10-IF(H48="",3,H48)/10-ROW()/1000000) | W48: =IF(V48="","",COUNTIF($V$5:$V$405,">"&V48)+1)
A49: 17tpepcpr2v | B49: Implementar informação da escolha das unidades/empreendimento no fluxo de permutas fora do terreno negociado no ClickUp | C49: Comercial Gadens | D49: Alexandre Marchiori Cruz | E49: sem prazo definido | G49: Definição ou decisão | O49: =IF(COUNT(I49:M49)<5,"",ROUND((I49*Matriz!$C$5+J49*Matriz!$C$6+K49*Matriz!$C$7+L49*Matriz!$C$8+M49*Matriz!$C$9)/SUM(Matriz!$C$5:$C$9),2)) | P49: =IFERROR(INDEX(Processos!$F$8:$F$17,MATCH(C49,Processos!$A$8:$A$17,0)),1) -> 1.017 | Q49: =IFERROR(INDEX(Matriz!$C$28:$C$33,MATCH(G49,Matriz!$A$28:$A$33,0)),0) -> 0 | R49: =IF(O49="","",ROUND(O49*P49+Q49,2)) | S49: =IF(R49="","",IF(R49>=Matriz!$C$19,4,IF(R49>=Matriz!$C$18,3,IF(R49>=Matriz!$C$17,2,1)))) | T49: =IF(S49="","",MAX(S49,IF(I49=5,Matriz!$C$23,0),IF(N49="Sim",Matriz!$C$24,0))) | U49: =IF(T49="","",CHOOSE(T49,"Baixa","Normal","Alta","Urgente")) | V49: =IF(T49="","",T49*1000+R49*10-IF(H49="",3,H49)/10-ROW()/1000000) | W49: =IF(V49="","",COUNTIF($V$5:$V$405,">"&V49)+1)
... A63: 17tpepcenqt | B63: Viabilizar o recebimento de propostas no CV e integrar com VPL - Gadens | C63: Comercial Gadens | D63: Alexandre Marchiori Cruz | E63: sem prazo definido | G63: Automação ou sistema | O63: =IF(COUNT(I63:M63)<5,"",ROUND((I63*Matriz!$C$5+J63*Matriz!$C$6+K63*Matriz!$C$7+L63*Matriz!$C$8+M63*Matriz!$C$9)/SUM(Matriz!$C$5:$C$9),2)) | P63: =IFERROR(INDEX(Processos!$F$8:$F$17,MATCH(C63,Processos!$A$8:$A$17,0)),1) -> 1.017 | Q63: =IFERROR(INDEX(Matriz!$C$28:$C$33,MATCH(G63,Matriz!$A$28:$A$33,0)),0) -> 0 | R63: =IF(O63="","",ROUND(O63*P63+Q63,2)) | S63: =IF(R63="","",IF(R63>=Matriz!$C$19,4,IF(R63>=Matriz!$C$18,3,IF(R63>=Matriz!$C$17,2,1)))) | T63: =IF(S63="","",MAX(S63,IF(I63=5,Matriz!$C$23,0),IF(N63="Sim",Matriz!$C$24,0))) | U63: =IF(T63="","",CHOOSE(T63,"Baixa","Normal","Alta","Urgente")) | V63: =IF(T63="","",T63*1000+R63*10-IF(H63="",3,H63)/10-ROW()/1000000) | W63: =IF(V63="","",COUNTIF($V$5:$V$405,">"&V63)+1)
A64: 17tpepcgphr | B64: Estabelecer controles para garantir o cumprimento da Política Comercial do Empreendimento | C64: Comercial Gadens | D64: Mônica Massaneiro | E64: pausado | G64: Controle | H64: 4 | I64: 4 | J64: 4 | K64: 1 | L64: 2 | M64: 3 | N64: Não | O64: =IF(COUNT(I64:M64)<5,"",ROUND((I64*Matriz!$C$5+J64*Matriz!$C$6+K64*Matriz!$C$7+L64*Matriz!$C$8+M64*Matriz!$C$9)/SUM(Matriz!$C$5:$C$9),2)) -> 2.95 | P64: =IFERROR(INDEX(Processos!$F$8:$F$17,MATCH(C64,Processos!$A$8:$A$17,0)),1) -> 1.017 | Q64: =IFERROR(INDEX(Matriz!$C$28:$C$33,MATCH(G64,Matriz!$A$28:$A$33,0)),0) -> 0.3 | R64: =IF(O64="","",ROUND(O64*P64+Q64,2)) -> 3.3 | S64: =IF(R64="","",IF(R64>=Matriz!$C$19,4,IF(R64>=Matriz!$C$18,3,IF(R64>=Matriz!$C$17,2,1)))) -> 3 | T64: =IF(S64="","",MAX(S64,IF(I64=5,Matriz!$C$23,0),IF(N64="Sim",Matriz!$C$24,0))) -> 3 | U64: =IF(T64="","",CHOOSE(T64,"Baixa","Normal","Alta","Urgente")) -> Alta | V64: =IF(T64="","",T64*1000+R64*10-IF(H64="",3,H64)/10-ROW()/1000000) -> 3032.5999 | W64: =IF(V64="","",COUNTIF($V$5:$V$405,">"&V64)+1) -> 7 | X64: Âncora (proposta) | Y64: Controle da Política Comercial: sem ele, condições de venda podem sair da regra.
A65: 17tpepcgqpc | B65: Avaliar análise de crédito complementar na modalidade associativo | C65: Comercial Make It | D65: Érica Ferreira Tavares Silva Caldeira, Cleverton Parnoff | E65: em progresso | F65: 46387 | G65: Definição ou decisão | O65: =IF(COUNT(I65:M65)<5,"",ROUND((I65*Matriz!$C$5+J65*Matriz!$C$6+K65*Matriz!$C$7+L65*Matriz!$C$8+M65*Matriz!$C$9)/SUM(Matriz!$C$5:$C$9),2)) | P65: =IFERROR(INDEX(Processos!$F$8:$F$17,MATCH(C65,Processos!$A$8:$A$17,0)),1) -> 1.034 | Q65: =IFERROR(INDEX(Matriz!$C$28:$C$33,MATCH(G65,Matriz!$A$28:$A$33,0)),0) -> 0 | R65: =IF(O65="","",ROUND(O65*P65+Q65,2)) | S65: =IF(R65="","",IF(R65>=Matriz!$C$19,4,IF(R65>=Matriz!$C$18,3,IF(R65>=Matriz!$C$17,2,1)))) | T65: =IF(S65="","",MAX(S65,IF(I65=5,Matriz!$C$23,0),IF(N65="Sim",Matriz!$C$24,0))) | U65: =IF(T65="","",CHOOSE(T65,"Baixa","Normal","Alta","Urgente")) | V65: =IF(T65="","",T65*1000+R65*10-IF(H65="",3,H65)/10-ROW()/1000000) | W65: =IF(V65="","",COUNTIF($V$5:$V$405,">"&V65)+1)
A66: 17tpepcgqwv | B66: Avaliar análise de crédito complementar na modalidade bancário | C66: Comercial Make It | D66: Érica Ferreira Tavares Silva Caldeira, Cleverton Parnoff | E66: em progresso | F66: 46387 | G66: Definição ou decisão | O66: =IF(COUNT(I66:M66)<5,"",ROUND((I66*Matriz!$C$5+J66*Matriz!$C$6+K66*Matriz!$C$7+L66*Matriz!$C$8+M66*Matriz!$C$9)/SUM(Matriz!$C$5:$C$9),2)) | P66: =IFERROR(INDEX(Processos!$F$8:$F$17,MATCH(C66,Processos!$A$8:$A$17,0)),1) -> 1.034 | Q66: =IFERROR(INDEX(Matriz!$C$28:$C$33,MATCH(G66,Matriz!$A$28:$A$33,0)),0) -> 0 | R66: =IF(O66="","",ROUND(O66*P66+Q66,2)) | S66: =IF(R66="","",IF(R66>=Matriz!$C$19,4,IF(R66>=Matriz!$C$18,3,IF(R66>=Matriz!$C$17,2,1)))) | T66: =IF(S66="","",MAX(S66,IF(I66=5,Matriz!$C$23,0),IF(N66="Sim",Matriz!$C$24,0))) | U66: =IF(T66="","",CHOOSE(T66,"Baixa","Normal","Alta","Urgente")) | V66: =IF(T66="","",T66*1000+R66*10-IF(H66="",3,H66)/10-ROW()/1000000) | W66: =IF(V66="","",COUNTIF($V$5:$V$405,">"&V66)+1)
A67: 17tpepcdam8 | B67: Avaliar análise de crédito interna para modalidade bancária | C67: Comercial Make It | D67: Érica Ferreira Tavares Silva Caldeira, Cleverton Parnoff | E67: em progresso | F67: 46387 | G67: Definição ou decisão | O67: =IF(COUNT(I67:M67)<5,"",ROUND((I67*Matriz!$C$5+J67*Matriz!$C$6+K67*Matriz!$C$7+L67*Matriz!$C$8+M67*Matriz!$C$9)/SUM(Matriz!$C$5:$C$9),2)) | P67: =IFERROR(INDEX(Processos!$F$8:$F$17,MATCH(C67,Processos!$A$8:$A$17,0)),1) -> 1.034 | Q67: =IFERROR(INDEX(Matriz!$C$28:$C$33,MATCH(G67,Matriz!$A$28:$A$33,0)),0) -> 0 | R67: =IF(O67="","",ROUND(O67*P67+Q67,2)) | S67: =IF(R67="","",IF(R67>=Matriz!$C$19,4,IF(R67>=Matriz!$C$18,3,IF(R67>=Matriz!$C$17,2,1)))) | T67: =IF(S67="","",MAX(S67,IF(I67=5,Matriz!$C$23,0),IF(N67="Sim",Matriz!$C$24,0))) | U67: =IF(T67="","",CHOOSE(T67,"Baixa","Normal","Alta","Urgente")) | V67: =IF(T67="","",T67*1000+R67*10-IF(H67="",3,H67)/10-ROW()/1000000) | W67: =IF(V67="","",COUNTIF($V$5:$V$405,">"&V67)+1)
A68: 17tpepcgq9c | B68: Elaborar Fluxo - Tapumes | C68: Comercial Make It | D68: Andrei Souza Santos | E68: em progresso | F68: 46387 | G68: Definição ou decisão | O68: =IF(COUNT(I68:M68)<5,"",ROUND((I68*Matriz!$C$5+J68*Matriz!$C$6+K68*Matriz!$C$7+L68*Matriz!$C$8+M68*Matriz!$C$9)/SUM(Matriz!$C$5:$C$9),2)) | P68: =IFERROR(INDEX(Processos!$F$8:$F$17,MATCH(C68,Processos!$A$8:$A$17,0)),1) -> 1.034 | Q68: =IFERROR(INDEX(Matriz!$C$28:$C$33,MATCH(G68,Matriz!$A$28:$A$33,0)),0) -> 0 | R68: =IF(O68="","",ROUND(O68*P68+Q68,2)) | S68: =IF(R68="","",IF(R68>=Matriz!$C$19,4,IF(R68>=Matriz!$C$18,3,IF(R68>=Matriz!$C$17,2,1)))) | T68: =IF(S68="","",MAX(S68,IF(I68=5,Matriz!$C$23,0),IF(N68="Sim",Matriz!$C$24,0))) | U68: =IF(T68="","",CHOOSE(T68,"Baixa","Normal","Alta","Urgente")) | V68: =IF(T68="","",T68*1000+R68*10-IF(H68="",3,H68)/10-ROW()/1000000) | W68: =IF(V68="","",COUNTIF($V$5:$V$405,">"&V68)+1)
A69: 17tpepcgpg0 | B69: Elaborar POP - Definição de Tabela de Preço | C69: Comercial Make It | D69: André Garcia Vilas Boas | E69: em progresso | F69: 46356 | G69: Documento normativo | O69: =IF(COUNT(I69:M69)<5,"",ROUND((I69*Matriz!$C$5+J69*Matriz!$C$6+K69*Matriz!$C$7+L69*Matriz!$C$8+M69*Matriz!$C$9)/SUM(Matriz!$C$5:$C$9),2)) | P69: =IFERROR(INDEX(Processos!$F$8:$F$17,MATCH(C69,Processos!$A$8:$A$17,0)),1) -> 1.034 | Q69: =IFERROR(INDEX(Matriz!$C$28:$C$33,MATCH(G69,Matriz!$A$28:$A$33,0)),0) -> 0 | R69: =IF(O69="","",ROUND(O69*P69+Q69,2)) | S69: =IF(R69="","",IF(R69>=Matriz!$C$19,4,IF(R69>=Matriz!$C$18,3,IF(R69>=Matriz!$C$17,2,1)))) | T69: =IF(S69="","",MAX(S69,IF(I69=5,Matriz!$C$23,0),IF(N69="Sim",Matriz!$C$24,0))) | U69: =IF(T69="","",CHOOSE(T69,"Baixa","Normal","Alta","Urgente")) | V69: =IF(T69="","",T69*1000+R69*10-IF(H69="",3,H69)/10-ROW()/1000000) | W69: =IF(V69="","",COUNTIF($V$5:$V$405,">"&V69)+1)
A70: 17tpepcgpg1 | B70: Elaborar POP - Procedimento Comercial do Empreendimento (Prazo, Condição de Pagamento, Riscos, modalidade e fonte de recurso, campanhas por empreendimento, etc.) | C70: Comercial Make It | D70: André Garcia Vilas Boas | E70: em progresso | F70: 46418 | G70: Documento normativo | O70: =IF(COUNT(I70:M70)<5,"",ROUND((I70*Matriz!$C$5+J70*Matriz!$C$6+K70*Matriz!$C$7+L70*Matriz!$C$8+M70*Matriz!$C$9)/SUM(Matriz!$C$5:$C$9),2)) | P70: =IFERROR(INDEX(Processos!$F$8:$F$17,MATCH(C70,Processos!$A$8:$A$17,0)),1) -> 1.034 | Q70: =IFERROR(INDEX(Matriz!$C$28:$C$33,MATCH(G70,Matriz!$A$28:$A$33,0)),0) -> 0 | R70: =IF(O70="","",ROUND(O70*P70+Q70,2)) | S70: =IF(R70="","",IF(R70>=Matriz!$C$19,4,IF(R70>=Matriz!$C$18,3,IF(R70>=Matriz!$C$17,2,1)))) | T70: =IF(S70="","",MAX(S70,IF(I70=5,Matriz!$C$23,0),IF(N70="Sim",Matriz!$C$24,0))) | U70: =IF(T70="","",CHOOSE(T70,"Baixa","Normal","Alta","Urgente")) | V70: =IF(T70="","",T70*1000+R70*10-IF(H70="",3,H70)/10-ROW()/1000000) | W70: =IF(V70="","",COUNTIF($V$5:$V$405,">"&V70)+1)
A71: 17tpepcent3 | B71: Elaborar POP ou Política - Premissas Validação da Análise de Crédito Make It | C71: Comercial Make It | D71: Cleverton Parnoff | E71: em progresso | F71: 46387 | G71: Documento normativo | O71: =IF(COUNT(I71:M71)<5,"",ROUND((I71*Matriz!$C$5+J71*Matriz!$C$6+K71*Matriz!$C$7+L71*Matriz!$C$8+M71*Matriz!$C$9)/SUM(Matriz!$C$5:$C$9),2)) | P71: =IFERROR(INDEX(Processos!$F$8:$F$17,MATCH(C71,Processos!$A$8:$A$17,0)),1) -> 1.034 | Q71: =IFERROR(INDEX(Matriz!$C$28:$C$33,MATCH(G71,Matriz!$A$28:$A$33,0)),0) -> 0 | R71: =IF(O71="","",ROUND(O71*P71+Q71,2)) | S71: =IF(R71="","",IF(R71>=Matriz!$C$19,4,IF(R71>=Matriz!$C$18,3,IF(R71>=Matriz!$C$17,2,1)))) | T71: =IF(S71="","",MAX(S71,IF(I71=5,Matriz!$C$23,0),IF(N71="Sim",Matriz!$C$24,0))) | U71: =IF(T71="","",CHOOSE(T71,"Baixa","Normal","Alta","Urgente")) | V71: =IF(T71="","",T71*1000+R71*10-IF(H71="",3,H71)/10-ROW()/1000000) | W71: =IF(V71="","",COUNTIF($V$5:$V$405,">"&V71)+1)
A72: 17tpepcdahb | B72: Implantar formalização de contratação com as imobiliárias selecionadas/Correspondentes (Contrato de Parceiria - Foco LGPD) | C72: Comercial Make It | D72: Edgard Machado Ferreira Junior | E72: em progresso | F72: 46387 | G72: Definição ou decisão | O72: =IF(COUNT(I72:M72)<5,"",ROUND((I72*Matriz!$C$5+J72*Matriz!$C$6+K72*Matriz!$C$7+L72*Matriz!$C$8+M72*Matriz!$C$9)/SUM(Matriz!$C$5:$C$9),2)) | P72: =IFERROR(INDEX(Processos!$F$8:$F$17,MATCH(C72,Processos!$A$8:$A$17,0)),1) -> 1.034 | Q72: =IFERROR(INDEX(Matriz!$C$28:$C$33,MATCH(G72,Matriz!$A$28:$A$33,0)),0) -> 0 | R72: =IF(O72="","",ROUND(O72*P72+Q72,2)) | S72: =IF(R72="","",IF(R72>=Matriz!$C$19,4,IF(R72>=Matriz!$C$18,3,IF(R72>=Matriz!$C$17,2,1)))) | T72: =IF(S72="","",MAX(S72,IF(I72=5,Matriz!$C$23,0),IF(N72="Sim",Matriz!$C$24,0))) | U72: =IF(T72="","",CHOOSE(T72,"Baixa","Normal","Alta","Urgente")) | V72: =IF(T72="","",T72*1000+R72*10-IF(H72="",3,H72)/10-ROW()/1000000) | W72: =IF(V72="","",COUNTIF($V$5:$V$405,">"&V72)+1)
A73: 17tpepcdaeg | B73: Melhorar o processo de análise crédito do cliente | C73: Comercial Make It | D73: Danielle Moraes | E73: em progresso | F73: 46418 | G73: Definição ou decisão | O73: =IF(COUNT(I73:M73)<5,"",ROUND((I73*Matriz!$C$5+J73*Matriz!$C$6+K73*Matriz!$C$7+L73*Matriz!$C$8+M73*Matriz!$C$9)/SUM(Matriz!$C$5:$C$9),2)) | P73: =IFERROR(INDEX(Processos!$F$8:$F$17,MATCH(C73,Processos!$A$8:$A$17,0)),1) -> 1.034 | Q73: =IFERROR(INDEX(Matriz!$C$28:$C$33,MATCH(G73,Matriz!$A$28:$A$33,0)),0) -> 0 | R73: =IF(O73="","",ROUND(O73*P73+Q73,2)) | S73: =IF(R73="","",IF(R73>=Matriz!$C$19,4,IF(R73>=Matriz!$C$18,3,IF(R73>=Matriz!$C$17,2,1)))) | T73: =IF(S73="","",MAX(S73,IF(I73=5,Matriz!$C$23,0),IF(N73="Sim",Matriz!$C$24,0))) | U73: =IF(T73="","",CHOOSE(T73,"Baixa","Normal","Alta","Urgente")) | V73: =IF(T73="","",T73*1000+R73*10-IF(H73="",3,H73)/10-ROW()/1000000) | W73: =IF(V73="","",COUNTIF($V$5:$V$405,">"&V73)+1)
A74: 17tpepcdaha | B74: Revisar proposta para adequar à LGPD | C74: Comercial Make It | D74: Edgard Machado Ferreira Junior | E74: em progresso | F74: 46387 | G74: Definição ou decisão | O74: =IF(COUNT(I74:M74)<5,"",ROUND((I74*Matriz!$C$5+J74*Matriz!$C$6+K74*Matriz!$C$7+L74*Matriz!$C$8+M74*Matriz!$C$9)/SUM(Matriz!$C$5:$C$9),2)) | P74: =IFERROR(INDEX(Processos!$F$8:$F$17,MATCH(C74,Processos!$A$8:$A$17,0)),1) -> 1.034 | Q74: =IFERROR(INDEX(Matriz!$C$28:$C$33,MATCH(G74,Matriz!$A$28:$A$33,0)),0) -> 0 | R74: =IF(O74="","",ROUND(O74*P74+Q74,2)) | S74: =IF(R74="","",IF(R74>=Matriz!$C$19,4,IF(R74>=Matriz!$C$18,3,IF(R74>=Matriz!$C$17,2,1)))) | T74: =IF(S74="","",MAX(S74,IF(I74=5,Matriz!$C$23,0),IF(N74="Sim",Matriz!$C$24,0))) | U74: =IF(T74="","",CHOOSE(T74,"Baixa","Normal","Alta","Urgente")) | V74: =IF(T74="","",T74*1000+R74*10-IF(H74="",3,H74)/10-ROW()/1000000) | W74: =IF(V74="","",COUNTIF($V$5:$V$405,">"&V74)+1)
A75: 17tpepcprje | B75: Adequar fluxo do ClickUp de abertura de SPEs para incluir quais estão disponíveis para NN | C75: Comercial Make It | D75: Edgard Machado Ferreira Junior | E75: sem prazo definido | G75: Definição ou decisão | O75: =IF(COUNT(I75:M75)<5,"",ROUND((I75*Matriz!$C$5+J75*Matriz!$C$6+K75*Matriz!$C$7+L75*Matriz!$C$8+M75*Matriz!$C$9)/SUM(Matriz!$C$5:$C$9),2)) | P75: =IFERROR(INDEX(Processos!$F$8:$F$17,MATCH(C75,Processos!$A$8:$A$17,0)),1) -> 1.034 | Q75: =IFERROR(INDEX(Matriz!$C$28:$C$33,MATCH(G75,Matriz!$A$28:$A$33,0)),0) -> 0 | R75: =IF(O75="","",ROUND(O75*P75+Q75,2)) | S75: =IF(R75="","",IF(R75>=Matriz!$C$19,4,IF(R75>=Matriz!$C$18,3,IF(R75>=Matriz!$C$17,2,1)))) | T75: =IF(S75="","",MAX(S75,IF(I75=5,Matriz!$C$23,0),IF(N75="Sim",Matriz!$C$24,0))) | U75: =IF(T75="","",CHOOSE(T75,"Baixa","Normal","Alta","Urgente")) | V75: =IF(T75="","",T75*1000+R75*10-IF(H75="",3,H75)/10-ROW()/1000000) | W75: =IF(V75="","",COUNTIF($V$5:$V$405,">"&V75)+1)
A76: 17tpepcghca | B76: Automatizar baixa da reserva no CV | C76: Comercial Make It | D76: Alexandre Marchiori Cruz | E76: sem prazo definido | G76: Automação ou sistema | O76: =IF(COUNT(I76:M76)<5,"",ROUND((I76*Matriz!$C$5+J76*Matriz!$C$6+K76*Matriz!$C$7+L76*Matriz!$C$8+M76*Matriz!$C$9)/SUM(Matriz!$C$5:$C$9),2)) | P76: =IFERROR(INDEX(Processos!$F$8:$F$17,MATCH(C76,Processos!$A$8:$A$17,0)),1) -> 1.034 | Q76: =IFERROR(INDEX(Matriz!$C$28:$C$33,MATCH(G76,Matriz!$A$28:$A$33,0)),0) -> 0 | R76: =IF(O76="","",ROUND(O76*P76+Q76,2)) | S76: =IF(R76="","",IF(R76>=Matriz!$C$19,4,IF(R76>=Matriz!$C$18,3,IF(R76>=Matriz!$C$17,2,1)))) | T76: =IF(S76="","",MAX(S76,IF(I76=5,Matriz!$C$23,0),IF(N76="Sim",Matriz!$C$24,0))) | U76: =IF(T76="","",CHOOSE(T76,"Baixa","Normal","Alta","Urgente")) | V76: =IF(T76="","",T76*1000+R76*10-IF(H76="",3,H76)/10-ROW()/1000000) | W76: =IF(V76="","",COUNTIF($V$5:$V$405,">"&V76)+1)
A77: 17tpepcghcc | B77: Automatizar data da venda e competência do contrato | C77: Comercial Make It | D77: Alexandre Marchiori Cruz | E77: sem prazo definido | G77: Automação ou sistema | O77: =IF(COUNT(I77:M77)<5,"",ROUND((I77*Matriz!$C$5+J77*Matriz!$C$6+K77*Matriz!$C$7+L77*Matriz!$C$8+M77*Matriz!$C$9)/SUM(Matriz!$C$5:$C$9),2)) | P77: =IFERROR(INDEX(Processos!$F$8:$F$17,MATCH(C77,Processos!$A$8:$A$17,0)),1) -> 1.034 | Q77: =IFERROR(INDEX(Matriz!$C$28:$C$33,MATCH(G77,Matriz!$A$28:$A$33,0)),0) -> 0 | R77: =IF(O77="","",ROUND(O77*P77+Q77,2)) | S77: =IF(R77="","",IF(R77>=Matriz!$C$19,4,IF(R77>=Matriz!$C$18,3,IF(R77>=Matriz!$C$17,2,1)))) | T77: =IF(S77="","",MAX(S77,IF(I77=5,Matriz!$C$23,0),IF(N77="Sim",Matriz!$C$24,0))) | U77: =IF(T77="","",CHOOSE(T77,"Baixa","Normal","Alta","Urgente")) | V77: =IF(T77="","",T77*1000+R77*10-IF(H77="",3,H77)/10-ROW()/1000000) | W77: =IF(V77="","",COUNTIF($V$5:$V$405,">"&V77)+1)
A78: 17tpepcprj7 | B78: Automatizar informação de decisão de opção de planta escolhida pelo cliente, via CV, para Planejamento e Controle | C78: Comercial Make It | D78: Alexandre Marchiori Cruz | E78: sem prazo definido | G78: Automação ou sistema | O78: =IF(COUNT(I78:M78)<5,"",ROUND((I78*Matriz!$C$5+J78*Matriz!$C$6+K78*Matriz!$C$7+L78*Matriz!$C$8+M78*Matriz!$C$9)/SUM(Matriz!$C$5:$C$9),2)) | P78: =IFERROR(INDEX(Processos!$F$8:$F$17,MATCH(C78,Processos!$A$8:$A$17,0)),1) -> 1.034 | Q78: =IFERROR(INDEX(Matriz!$C$28:$C$33,MATCH(G78,Matriz!$A$28:$A$33,0)),0) -> 0 | R78: =IF(O78="","",ROUND(O78*P78+Q78,2)) | S78: =IF(R78="","",IF(R78>=Matriz!$C$19,4,IF(R78>=Matriz!$C$18,3,IF(R78>=Matriz!$C$17,2,1)))) | T78: =IF(S78="","",MAX(S78,IF(I78=5,Matriz!$C$23,0),IF(N78="Sim",Matriz!$C$24,0))) | U78: =IF(T78="","",CHOOSE(T78,"Baixa","Normal","Alta","Urgente")) | V78: =IF(T78="","",T78*1000+R78*10-IF(H78="",3,H78)/10-ROW()/1000000) | W78: =IF(V78="","",COUNTIF($V$5:$V$405,">"&V78)+1)
A79: 17tpepcenrn | B79: Automatizar processo de contratação com imobiliárias selecionadas | C79: Comercial Make It | D79: Alexandre Marchiori Cruz | E79: sem prazo definido | G79: Automação ou sistema | O79: =IF(COUNT(I79:M79)<5,"",ROUND((I79*Matriz!$C$5+J79*Matriz!$C$6+K79*Matriz!$C$7+L79*Matriz!$C$8+M79*Matriz!$C$9)/SUM(Matriz!$C$5:$C$9),2)) | P79: =IFERROR(INDEX(Processos!$F$8:$F$17,MATCH(C79,Processos!$A$8:$A$17,0)),1) -> 1.034 | Q79: =IFERROR(INDEX(Matriz!$C$28:$C$33,MATCH(G79,Matriz!$A$28:$A$33,0)),0) -> 0 | R79: =IF(O79="","",ROUND(O79*P79+Q79,2)) | S79: =IF(R79="","",IF(R79>=Matriz!$C$19,4,IF(R79>=Matriz!$C$18,3,IF(R79>=Matriz!$C$17,2,1)))) | T79: =IF(S79="","",MAX(S79,IF(I79=5,Matriz!$C$23,0),IF(N79="Sim",Matriz!$C$24,0))) | U79: =IF(T79="","",CHOOSE(T79,"Baixa","Normal","Alta","Urgente")) | V79: =IF(T79="","",T79*1000+R79*10-IF(H79="",3,H79)/10-ROW()/1000000) | W79: =IF(V79="","",COUNTIF($V$5:$V$405,">"&V79)+1)
A80: 17tpepcekpq | B80: Avaliar automatização do processo de leads - WhatsApp vs CV Make It | C80: Comercial Make It | D80: Alexandre Marchiori Cruz | E80: sem prazo definido | G80: Automação ou sistema | O80: =IF(COUNT(I80:M80)<5,"",ROUND((I80*Matriz!$C$5+J80*Matriz!$C$6+K80*Matriz!$C$7+L80*Matriz!$C$8+M80*Matriz!$C$9)/SUM(Matriz!$C$5:$C$9),2)) | P80: =IFERROR(INDEX(Processos!$F$8:$F$17,MATCH(C80,Processos!$A$8:$A$17,0)),1) -> 1.034 | Q80: =IFERROR(INDEX(Matriz!$C$28:$C$33,MATCH(G80,Matriz!$A$28:$A$33,0)),0) -> 0 | R80: =IF(O80="","",ROUND(O80*P80+Q80,2)) | S80: =IF(R80="","",IF(R80>=Matriz!$C$19,4,IF(R80>=Matriz!$C$18,3,IF(R80>=Matriz!$C$17,2,1)))) | T80: =IF(S80="","",MAX(S80,IF(I80=5,Matriz!$C$23,0),IF(N80="Sim",Matriz!$C$24,0))) | U80: =IF(T80="","",CHOOSE(T80,"Baixa","Normal","Alta","Urgente")) | V80: =IF(T80="","",T80*1000+R80*10-IF(H80="",3,H80)/10-ROW()/1000000) | W80: =IF(V80="","",COUNTIF($V$5:$V$405,">"&V80)+1)
A81: 17tpepcprk9 | B81: Avaliar bloqueio de unidades permutadas dentro do Mega a partir do CV | C81: Comercial Make It | D81: Alexandre Marchiori Cruz | E81: sem prazo definido | G81: Controle | O81: =IF(COUNT(I81:M81)<5,"",ROUND((I81*Matriz!$C$5+J81*Matriz!$C$6+K81*Matriz!$C$7+L81*Matriz!$C$8+M81*Matriz!$C$9)/SUM(Matriz!$C$5:$C$9),2)) | P81: =IFERROR(INDEX(Processos!$F$8:$F$17,MATCH(C81,Processos!$A$8:$A$17,0)),1) -> 1.034 | Q81: =IFERROR(INDEX(Matriz!$C$28:$C$33,MATCH(G81,Matriz!$A$28:$A$33,0)),0) -> 0.3 | R81: =IF(O81="","",ROUND(O81*P81+Q81,2)) | S81: =IF(R81="","",IF(R81>=Matriz!$C$19,4,IF(R81>=Matriz!$C$18,3,IF(R81>=Matriz!$C$17,2,1)))) | T81: =IF(S81="","",MAX(S81,IF(I81=5,Matriz!$C$23,0),IF(N81="Sim",Matriz!$C$24,0))) | U81: =IF(T81="","",CHOOSE(T81,"Baixa","Normal","Alta","Urgente")) | V81: =IF(T81="","",T81*1000+R81*10-IF(H81="",3,H81)/10-ROW()/1000000) | W81: =IF(V81="","",COUNTIF($V$5:$V$405,">"&V81)+1)
A82: 17tpepcprj5 | B82: Avaliar com as construtoras prazo máximo para alteração de opção de planta | C82: Comercial Make It | D82: Hellen Venturoso | E82: sem prazo definido | G82: Definição ou decisão | O82: =IF(COUNT(I82:M82)<5,"",ROUND((I82*Matriz!$C$5+J82*Matriz!$C$6+K82*Matriz!$C$7+L82*Matriz!$C$8+M82*Matriz!$C$9)/SUM(Matriz!$C$5:$C$9),2)) | P82: =IFERROR(INDEX(Processos!$F$8:$F$17,MATCH(C82,Processos!$A$8:$A$17,0)),1) -> 1.034 | Q82: =IFERROR(INDEX(Matriz!$C$28:$C$33,MATCH(G82,Matriz!$A$28:$A$33,0)),0) -> 0 | R82: =IF(O82="","",ROUND(O82*P82+Q82,2)) | S82: =IF(R82="","",IF(R82>=Matriz!$C$19,4,IF(R82>=Matriz!$C$18,3,IF(R82>=Matriz!$C$17,2,1)))) | T82: =IF(S82="","",MAX(S82,IF(I82=5,Matriz!$C$23,0),IF(N82="Sim",Matriz!$C$24,0))) | U82: =IF(T82="","",CHOOSE(T82,"Baixa","Normal","Alta","Urgente")) | V82: =IF(T82="","",T82*1000+R82*10-IF(H82="",3,H82)/10-ROW()/1000000) | W82: =IF(V82="","",COUNTIF($V$5:$V$405,">"&V82)+1)
A83: 17tpepcgqy3 | B83: Avaliar impacto da reforma tributária na migração de pessoa física para pessoa jurídica | C83: Comercial Make It | D83: Érica Ferreira Tavares Silva Caldeira | E83: sem prazo definido | G83: Definição ou decisão | O83: =IF(COUNT(I83:M83)<5,"",ROUND((I83*Matriz!$C$5+J83*Matriz!$C$6+K83*Matriz!$C$7+L83*Matriz!$C$8+M83*Matriz!$C$9)/SUM(Matriz!$C$5:$C$9),2)) | P83: =IFERROR(INDEX(Processos!$F$8:$F$17,MATCH(C83,Processos!$A$8:$A$17,0)),1) -> 1.034 | Q83: =IFERROR(INDEX(Matriz!$C$28:$C$33,MATCH(G83,Matriz!$A$28:$A$33,0)),0) -> 0 | R83: =IF(O83="","",ROUND(O83*P83+Q83,2)) | S83: =IF(R83="","",IF(R83>=Matriz!$C$19,4,IF(R83>=Matriz!$C$18,3,IF(R83>=Matriz!$C$17,2,1)))) | T83: =IF(S83="","",MAX(S83,IF(I83=5,Matriz!$C$23,0),IF(N83="Sim",Matriz!$C$24,0))) | U83: =IF(T83="","",CHOOSE(T83,"Baixa","Normal","Alta","Urgente")) | V83: =IF(T83="","",T83*1000+R83*10-IF(H83="",3,H83)/10-ROW()/1000000) | W83: =IF(V83="","",COUNTIF($V$5:$V$405,">"&V83)+1)
A84: 17tpepcprk2 | B84: Avaliar informação automática sobre cadastro do contrato de permuta financeira, através do Mega Inteligence, ou solução similar | C84: Comercial Make It | D84: Alexandre Marchiori Cruz | E84: sem prazo definido | G84: Automação ou sistema | O84: =IF(COUNT(I84:M84)<5,"",ROUND((I84*Matriz!$C$5+J84*Matriz!$C$6+K84*Matriz!$C$7+L84*Matriz!$C$8+M84*Matriz!$C$9)/SUM(Matriz!$C$5:$C$9),2)) | P84: =IFERROR(INDEX(Processos!$F$8:$F$17,MATCH(C84,Processos!$A$8:$A$17,0)),1) -> 1.034 | Q84: =IFERROR(INDEX(Matriz!$C$28:$C$33,MATCH(G84,Matriz!$A$28:$A$33,0)),0) -> 0 | R84: =IF(O84="","",ROUND(O84*P84+Q84,2)) | S84: =IF(R84="","",IF(R84>=Matriz!$C$19,4,IF(R84>=Matriz!$C$18,3,IF(R84>=Matriz!$C$17,2,1)))) | T84: =IF(S84="","",MAX(S84,IF(I84=5,Matriz!$C$23,0),IF(N84="Sim",Matriz!$C$24,0))) | U84: =IF(T84="","",CHOOSE(T84,"Baixa","Normal","Alta","Urgente")) | V84: =IF(T84="","",T84*1000+R84*10-IF(H84="",3,H84)/10-ROW()/1000000) | W84: =IF(V84="","",COUNTIF($V$5:$V$405,">"&V84)+1)
A85: 17tpepcprjm | B85: Avaliar padronização de nomenclatura das permutas / justificativas de bloqueio no CV (Make It e Gadens) | C85: Comercial Make It | D85: André Garcia Vilas Boas, Mônica Massaneiro | E85: sem prazo definido | G85: Controle | O85: =IF(COUNT(I85:M85)<5,"",ROUND((I85*Matriz!$C$5+J85*Matriz!$C$6+K85*Matriz!$C$7+L85*Matriz!$C$8+M85*Matriz!$C$9)/SUM(Matriz!$C$5:$C$9),2)) | P85: =IFERROR(INDEX(Processos!$F$8:$F$17,MATCH(C85,Processos!$A$8:$A$17,0)),1) -> 1.034 | Q85: =IFERROR(INDEX(Matriz!$C$28:$C$33,MATCH(G85,Matriz!$A$28:$A$33,0)),0) -> 0.3 | R85: =IF(O85="","",ROUND(O85*P85+Q85,2)) | S85: =IF(R85="","",IF(R85>=Matriz!$C$19,4,IF(R85>=Matriz!$C$18,3,IF(R85>=Matriz!$C$17,2,1)))) | T85: =IF(S85="","",MAX(S85,IF(I85=5,Matriz!$C$23,0),IF(N85="Sim",Matriz!$C$24,0))) | U85: =IF(T85="","",CHOOSE(T85,"Baixa","Normal","Alta","Urgente")) | V85: =IF(T85="","",T85*1000+R85*10-IF(H85="",3,H85)/10-ROW()/1000000) | W85: =IF(V85="","",COUNTIF($V$5:$V$405,">"&V85)+1)
A86: 17tpepcprk6 | B86: Avaliar qual melhor modelo para permuta intercompany e garantir aplicação no sistema e incluir no fluxo | C86: Comercial Make It | D86: Paulo Tavares | E86: sem prazo definido | G86: Automação ou sistema | O86: =IF(COUNT(I86:M86)<5,"",ROUND((I86*Matriz!$C$5+J86*Matriz!$C$6+K86*Matriz!$C$7+L86*Matriz!$C$8+M86*Matriz!$C$9)/SUM(Matriz!$C$5:$C$9),2)) | P86: =IFERROR(INDEX(Processos!$F$8:$F$17,MATCH(C86,Processos!$A$8:$A$17,0)),1) -> 1.034 | Q86: =IFERROR(INDEX(Matriz!$C$28:$C$33,MATCH(G86,Matriz!$A$28:$A$33,0)),0) -> 0 | R86: =IF(O86="","",ROUND(O86*P86+Q86,2)) | S86: =IF(R86="","",IF(R86>=Matriz!$C$19,4,IF(R86>=Matriz!$C$18,3,IF(R86>=Matriz!$C$17,2,1)))) | T86: =IF(S86="","",MAX(S86,IF(I86=5,Matriz!$C$23,0),IF(N86="Sim",Matriz!$C$24,0))) | U86: =IF(T86="","",CHOOSE(T86,"Baixa","Normal","Alta","Urgente")) | V86: =IF(T86="","",T86*1000+R86*10-IF(H86="",3,H86)/10-ROW()/1000000) | W86: =IF(V86="","",COUNTIF($V$5:$V$405,">"&V86)+1)
... A111: 17tpepcgpg2 | B111: Estabelecer controles para garantir o cumprimento da Política Comercial do Empreendimento | C111: Comercial Make It | D111: André Garcia Vilas Boas | E111: pausado | G111: Definição ou decisão | O111: =IF(COUNT(I111:M111)<5,"",ROUND((I111*Matriz!$C$5+J111*Matriz!$C$6+K111*Matriz!$C$7+L111*Matriz!$C$8+M111*Matriz!$C$9)/SUM(Matriz!$C$5:$C$9),2)) | P111: =IFERROR(INDEX(Processos!$F$8:$F$17,MATCH(C111,Processos!$A$8:$A$17,0)),1) -> 1.034 | Q111: =IFERROR(INDEX(Matriz!$C$28:$C$33,MATCH(G111,Matriz!$A$28:$A$33,0)),0) -> 0 | R111: =IF(O111="","",ROUND(O111*P111+Q111,2)) | S111: =IF(R111="","",IF(R111>=Matriz!$C$19,4,IF(R111>=Matriz!$C$18,3,IF(R111>=Matriz!$C$17,2,1)))) | T111: =IF(S111="","",MAX(S111,IF(I111=5,Matriz!$C$23,0),IF(N111="Sim",Matriz!$C$24,0))) | U111: =IF(T111="","",CHOOSE(T111,"Baixa","Normal","Alta","Urgente")) | V111: =IF(T111="","",T111*1000+R111*10-IF(H111="",3,H111)/10-ROW()/1000000) | W111: =IF(V111="","",COUNTIF($V$5:$V$405,">"&V111)+1)
A112: 86agdxvm8 | B112: Analisar a possibilidade de automatizar a inserção de dados no Maxor c/ gestão/comparação (atualmente esta fazendo no Excel). | C112: Engenharia | D112: Alexandre Marchiori Cruz | E112: em atraso | F112: 46203 | G112: Automação ou sistema | O112: =IF(COUNT(I112:M112)<5,"",ROUND((I112*Matriz!$C$5+J112*Matriz!$C$6+K112*Matriz!$C$7+L112*Matriz!$C$8+M112*Matriz!$C$9)/SUM(Matriz!$C$5:$C$9),2)) | P112: =IFERROR(INDEX(Processos!$F$8:$F$17,MATCH(C112,Processos!$A$8:$A$17,0)),1) -> 1.084 | Q112: =IFERROR(INDEX(Matriz!$C$28:$C$33,MATCH(G112,Matriz!$A$28:$A$33,0)),0) -> 0 | R112: =IF(O112="","",ROUND(O112*P112+Q112,2)) | S112: =IF(R112="","",IF(R112>=Matriz!$C$19,4,IF(R112>=Matriz!$C$18,3,IF(R112>=Matriz!$C$17,2,1)))) | T112: =IF(S112="","",MAX(S112,IF(I112=5,Matriz!$C$23,0),IF(N112="Sim",Matriz!$C$24,0))) | U112: =IF(T112="","",CHOOSE(T112,"Baixa","Normal","Alta","Urgente")) | V112: =IF(T112="","",T112*1000+R112*10-IF(H112="",3,H112)/10-ROW()/1000000) | W112: =IF(V112="","",COUNTIF($V$5:$V$405,">"&V112)+1)
A113: 86agjaf19 | B113: Aplicar as penalidades contempladas em contrato com a empreiteira/construtora quando do não cumprimento dos itens apontados na vistoria (Andressa / Apoio Alessandro e Hellen)" | C113: Engenharia | D113: Edgard Machado Ferreira Junior, Andressa Gazolla Gutmann | E113: em atraso | F113: 46173 | G113: Definição ou decisão | O113: =IF(COUNT(I113:M113)<5,"",ROUND((I113*Matriz!$C$5+J113*Matriz!$C$6+K113*Matriz!$C$7+L113*Matriz!$C$8+M113*Matriz!$C$9)/SUM(Matriz!$C$5:$C$9),2)) | P113: =IFERROR(INDEX(Processos!$F$8:$F$17,MATCH(C113,Processos!$A$8:$A$17,0)),1) -> 1.084 | Q113: =IFERROR(INDEX(Matriz!$C$28:$C$33,MATCH(G113,Matriz!$A$28:$A$33,0)),0) -> 0 | R113: =IF(O113="","",ROUND(O113*P113+Q113,2)) | S113: =IF(R113="","",IF(R113>=Matriz!$C$19,4,IF(R113>=Matriz!$C$18,3,IF(R113>=Matriz!$C$17,2,1)))) | T113: =IF(S113="","",MAX(S113,IF(I113=5,Matriz!$C$23,0),IF(N113="Sim",Matriz!$C$24,0))) | U113: =IF(T113="","",CHOOSE(T113,"Baixa","Normal","Alta","Urgente")) | V113: =IF(T113="","",T113*1000+R113*10-IF(H113="",3,H113)/10-ROW()/1000000) | W113: =IF(V113="","",COUNTIF($V$5:$V$405,">"&V113)+1)
A114: 86age41ph | B114: Automação do processo de aprovação e distribuição do orçamento executivo (conf. sub-processo "Desenvolve o orç. executivo (D+45)"). | C114: Engenharia | D114: Alexandre Marchiori Cruz | E114: em atraso | F114: 46203 | G114: Definição ou decisão | O114: =IF(COUNT(I114:M114)<5,"",ROUND((I114*Matriz!$C$5+J114*Matriz!$C$6+K114*Matriz!$C$7+L114*Matriz!$C$8+M114*Matriz!$C$9)/SUM(Matriz!$C$5:$C$9),2)) | P114: =IFERROR(INDEX(Processos!$F$8:$F$17,MATCH(C114,Processos!$A$8:$A$17,0)),1) -> 1.084 | Q114: =IFERROR(INDEX(Matriz!$C$28:$C$33,MATCH(G114,Matriz!$A$28:$A$33,0)),0) -> 0 | R114: =IF(O114="","",ROUND(O114*P114+Q114,2)) | S114: =IF(R114="","",IF(R114>=Matriz!$C$19,4,IF(R114>=Matriz!$C$18,3,IF(R114>=Matriz!$C$17,2,1)))) | T114: =IF(S114="","",MAX(S114,IF(I114=5,Matriz!$C$23,0),IF(N114="Sim",Matriz!$C$24,0))) | U114: =IF(T114="","",CHOOSE(T114,"Baixa","Normal","Alta","Urgente")) | V114: =IF(T114="","",T114*1000+R114*10-IF(H114="",3,H114)/10-ROW()/1000000) | W114: =IF(V114="","",COUNTIF($V$5:$V$405,">"&V114)+1)
A115: 86ah20vy7 | B115: Definir processo de contingência de orçamento pré-executivo (Make It) | C115: Engenharia | D115: Fernando Okraska, Leticia Gonçalves Bacchi | E115: em atraso | F115: 46265 | G115: Definição ou decisão | O115: =IF(COUNT(I115:M115)<5,"",ROUND((I115*Matriz!$C$5+J115*Matriz!$C$6+K115*Matriz!$C$7+L115*Matriz!$C$8+M115*Matriz!$C$9)/SUM(Matriz!$C$5:$C$9),2)) | P115: =IFERROR(INDEX(Processos!$F$8:$F$17,MATCH(C115,Processos!$A$8:$A$17,0)),1) -> 1.084 | Q115: =IFERROR(INDEX(Matriz!$C$28:$C$33,MATCH(G115,Matriz!$A$28:$A$33,0)),0) -> 0 | R115: =IF(O115="","",ROUND(O115*P115+Q115,2)) | S115: =IF(R115="","",IF(R115>=Matriz!$C$19,4,IF(R115>=Matriz!$C$18,3,IF(R115>=Matriz!$C$17,2,1)))) | T115: =IF(S115="","",MAX(S115,IF(I115=5,Matriz!$C$23,0),IF(N115="Sim",Matriz!$C$24,0))) | U115: =IF(T115="","",CHOOSE(T115,"Baixa","Normal","Alta","Urgente")) | V115: =IF(T115="","",T115*1000+R115*10-IF(H115="",3,H115)/10-ROW()/1000000) | W115: =IF(V115="","",COUNTIF($V$5:$V$405,">"&V115)+1)
A116: 86ajf8rr2 | B116: Definir responsabilidade pelo Tapume - Gadens e Make It | C116: Engenharia | D116: Andrei Souza Santos | E116: em atraso | F116: 46295 | G116: Definição ou decisão | O116: =IF(COUNT(I116:M116)<5,"",ROUND((I116*Matriz!$C$5+J116*Matriz!$C$6+K116*Matriz!$C$7+L116*Matriz!$C$8+M116*Matriz!$C$9)/SUM(Matriz!$C$5:$C$9),2)) | P116: =IFERROR(INDEX(Processos!$F$8:$F$17,MATCH(C116,Processos!$A$8:$A$17,0)),1) -> 1.084 | Q116: =IFERROR(INDEX(Matriz!$C$28:$C$33,MATCH(G116,Matriz!$A$28:$A$33,0)),0) -> 0 | R116: =IF(O116="","",ROUND(O116*P116+Q116,2)) | S116: =IF(R116="","",IF(R116>=Matriz!$C$19,4,IF(R116>=Matriz!$C$18,3,IF(R116>=Matriz!$C$17,2,1)))) | T116: =IF(S116="","",MAX(S116,IF(I116=5,Matriz!$C$23,0),IF(N116="Sim",Matriz!$C$24,0))) | U116: =IF(T116="","",CHOOSE(T116,"Baixa","Normal","Alta","Urgente")) | V116: =IF(T116="","",T116*1000+R116*10-IF(H116="",3,H116)/10-ROW()/1000000) | W116: =IF(V116="","",COUNTIF($V$5:$V$405,">"&V116)+1)
A117: 86aj7bmyf | B117: Elaborar POP - Critérios e diretrizes de avaliação de riscos, medidas de contenção de danos e minimização de impacto | C117: Engenharia | D117: Alessandro Braz | E117: em atraso | F117: 46265 | G117: Documento normativo | O117: =IF(COUNT(I117:M117)<5,"",ROUND((I117*Matriz!$C$5+J117*Matriz!$C$6+K117*Matriz!$C$7+L117*Matriz!$C$8+M117*Matriz!$C$9)/SUM(Matriz!$C$5:$C$9),2)) | P117: =IFERROR(INDEX(Processos!$F$8:$F$17,MATCH(C117,Processos!$A$8:$A$17,0)),1) -> 1.084 | Q117: =IFERROR(INDEX(Matriz!$C$28:$C$33,MATCH(G117,Matriz!$A$28:$A$33,0)),0) -> 0 | R117: =IF(O117="","",ROUND(O117*P117+Q117,2)) | S117: =IF(R117="","",IF(R117>=Matriz!$C$19,4,IF(R117>=Matriz!$C$18,3,IF(R117>=Matriz!$C$17,2,1)))) | T117: =IF(S117="","",MAX(S117,IF(I117=5,Matriz!$C$23,0),IF(N117="Sim",Matriz!$C$24,0))) | U117: =IF(T117="","",CHOOSE(T117,"Baixa","Normal","Alta","Urgente")) | V117: =IF(T117="","",T117*1000+R117*10-IF(H117="",3,H117)/10-ROW()/1000000) | W117: =IF(V117="","",COUNTIF($V$5:$V$405,">"&V117)+1)
A118: 86aj7bx9m | B118: Elaborar POP - Critérios e diretrizes de vistoria e revistoria de Qualidade - Finalização de Obra | C118: Engenharia | D118: Alessandro Braz | E118: em atraso | F118: 46265 | G118: Documento normativo | O118: =IF(COUNT(I118:M118)<5,"",ROUND((I118*Matriz!$C$5+J118*Matriz!$C$6+K118*Matriz!$C$7+L118*Matriz!$C$8+M118*Matriz!$C$9)/SUM(Matriz!$C$5:$C$9),2)) | P118: =IFERROR(INDEX(Processos!$F$8:$F$17,MATCH(C118,Processos!$A$8:$A$17,0)),1) -> 1.084 | Q118: =IFERROR(INDEX(Matriz!$C$28:$C$33,MATCH(G118,Matriz!$A$28:$A$33,0)),0) -> 0 | R118: =IF(O118="","",ROUND(O118*P118+Q118,2)) | S118: =IF(R118="","",IF(R118>=Matriz!$C$19,4,IF(R118>=Matriz!$C$18,3,IF(R118>=Matriz!$C$17,2,1)))) | T118: =IF(S118="","",MAX(S118,IF(I118=5,Matriz!$C$23,0),IF(N118="Sim",Matriz!$C$24,0))) | U118: =IF(T118="","",CHOOSE(T118,"Baixa","Normal","Alta","Urgente")) | V118: =IF(T118="","",T118*1000+R118*10-IF(H118="",3,H118)/10-ROW()/1000000) | W118: =IF(V118="","",COUNTIF($V$5:$V$405,">"&V118)+1)
A119: 86aj7bx9d | B119: Elaborar POP - Critérios e diretrizes de vistoria interna (Copel, Sanepar e concessionarias) Finalização de Obra | C119: Engenharia | D119: Lucas Lopes | E119: em atraso | F119: 46234 | G119: Documento normativo | O119: =IF(COUNT(I119:M119)<5,"",ROUND((I119*Matriz!$C$5+J119*Matriz!$C$6+K119*Matriz!$C$7+L119*Matriz!$C$8+M119*Matriz!$C$9)/SUM(Matriz!$C$5:$C$9),2)) | P119: =IFERROR(INDEX(Processos!$F$8:$F$17,MATCH(C119,Processos!$A$8:$A$17,0)),1) -> 1.084 | Q119: =IFERROR(INDEX(Matriz!$C$28:$C$33,MATCH(G119,Matriz!$A$28:$A$33,0)),0) -> 0 | R119: =IF(O119="","",ROUND(O119*P119+Q119,2)) | S119: =IF(R119="","",IF(R119>=Matriz!$C$19,4,IF(R119>=Matriz!$C$18,3,IF(R119>=Matriz!$C$17,2,1)))) | T119: =IF(S119="","",MAX(S119,IF(I119=5,Matriz!$C$23,0),IF(N119="Sim",Matriz!$C$24,0))) | U119: =IF(T119="","",CHOOSE(T119,"Baixa","Normal","Alta","Urgente")) | V119: =IF(T119="","",T119*1000+R119*10-IF(H119="",3,H119)/10-ROW()/1000000) | W119: =IF(V119="","",COUNTIF($V$5:$V$405,">"&V119)+1)
A120: 86aj7b0ue | B120: Elaborar POP - Estrutura e diretrizes de projeto de TAP | C120: Engenharia | D120: Lucas Lopes | E120: em atraso | F120: 46295 | G120: Documento normativo | O120: =IF(COUNT(I120:M120)<5,"",ROUND((I120*Matriz!$C$5+J120*Matriz!$C$6+K120*Matriz!$C$7+L120*Matriz!$C$8+M120*Matriz!$C$9)/SUM(Matriz!$C$5:$C$9),2)) | P120: =IFERROR(INDEX(Processos!$F$8:$F$17,MATCH(C120,Processos!$A$8:$A$17,0)),1) -> 1.084 | Q120: =IFERROR(INDEX(Matriz!$C$28:$C$33,MATCH(G120,Matriz!$A$28:$A$33,0)),0) -> 0 | R120: =IF(O120="","",ROUND(O120*P120+Q120,2)) | S120: =IF(R120="","",IF(R120>=Matriz!$C$19,4,IF(R120>=Matriz!$C$18,3,IF(R120>=Matriz!$C$17,2,1)))) | T120: =IF(S120="","",MAX(S120,IF(I120=5,Matriz!$C$23,0),IF(N120="Sim",Matriz!$C$24,0))) | U120: =IF(T120="","",CHOOSE(T120,"Baixa","Normal","Alta","Urgente")) | V120: =IF(T120="","",T120*1000+R120*10-IF(H120="",3,H120)/10-ROW()/1000000) | W120: =IF(V120="","",COUNTIF($V$5:$V$405,">"&V120)+1)
A121: 86agv9x68 | B121: Elaborar POP - Lista de escopo que não deveria ser alterada (ex. fundação, quadro, esquadrilha, vedação, posicionamento do esquadro) - Lucas Lopes + Talita e Nadi | C121: Engenharia | D121: Lucas Lopes, Fernando Okraska | E121: em atraso | F121: 46203 | G121: Documento normativo | O121: =IF(COUNT(I121:M121)<5,"",ROUND((I121*Matriz!$C$5+J121*Matriz!$C$6+K121*Matriz!$C$7+L121*Matriz!$C$8+M121*Matriz!$C$9)/SUM(Matriz!$C$5:$C$9),2)) | P121: =IFERROR(INDEX(Processos!$F$8:$F$17,MATCH(C121,Processos!$A$8:$A$17,0)),1) -> 1.084 | Q121: =IFERROR(INDEX(Matriz!$C$28:$C$33,MATCH(G121,Matriz!$A$28:$A$33,0)),0) -> 0 | R121: =IF(O121="","",ROUND(O121*P121+Q121,2)) | S121: =IF(R121="","",IF(R121>=Matriz!$C$19,4,IF(R121>=Matriz!$C$18,3,IF(R121>=Matriz!$C$17,2,1)))) | T121: =IF(S121="","",MAX(S121,IF(I121=5,Matriz!$C$23,0),IF(N121="Sim",Matriz!$C$24,0))) | U121: =IF(T121="","",CHOOSE(T121,"Baixa","Normal","Alta","Urgente")) | V121: =IF(T121="","",T121*1000+R121*10-IF(H121="",3,H121)/10-ROW()/1000000) | W121: =IF(V121="","",COUNTIF($V$5:$V$405,">"&V121)+1)
A122: 86agzka6x | B122: Elaborar POP - Padrão de Visita Guiada - Gadens e Make It | C122: Engenharia | D122: Andrei Souza Santos | E122: em atraso | F122: 46295 | G122: Documento normativo | O122: =IF(COUNT(I122:M122)<5,"",ROUND((I122*Matriz!$C$5+J122*Matriz!$C$6+K122*Matriz!$C$7+L122*Matriz!$C$8+M122*Matriz!$C$9)/SUM(Matriz!$C$5:$C$9),2)) | P122: =IFERROR(INDEX(Processos!$F$8:$F$17,MATCH(C122,Processos!$A$8:$A$17,0)),1) -> 1.084 | Q122: =IFERROR(INDEX(Matriz!$C$28:$C$33,MATCH(G122,Matriz!$A$28:$A$33,0)),0) -> 0 | R122: =IF(O122="","",ROUND(O122*P122+Q122,2)) | S122: =IF(R122="","",IF(R122>=Matriz!$C$19,4,IF(R122>=Matriz!$C$18,3,IF(R122>=Matriz!$C$17,2,1)))) | T122: =IF(S122="","",MAX(S122,IF(I122=5,Matriz!$C$23,0),IF(N122="Sim",Matriz!$C$24,0))) | U122: =IF(T122="","",CHOOSE(T122,"Baixa","Normal","Alta","Urgente")) | V122: =IF(T122="","",T122*1000+R122*10-IF(H122="",3,H122)/10-ROW()/1000000) | W122: =IF(V122="","",COUNTIF($V$5:$V$405,">"&V122)+1)
A123: 86ahckp0b | B123: Elaborar POP - Procedimento de interrupção de obra por motivos de segurança POP | C123: Engenharia | D123: Alessandro Braz | E123: em atraso | F123: 46265 | G123: Documento normativo | H123: 3 | I123: 4 | J123: 3 | K123: 5 | L123: 5 | M123: 3 | N123: Não | O123: =IF(COUNT(I123:M123)<5,"",ROUND((I123*Matriz!$C$5+J123*Matriz!$C$6+K123*Matriz!$C$7+L123*Matriz!$C$8+M123*Matriz!$C$9)/SUM(Matriz!$C$5:$C$9),2)) -> 4 | P123: =IFERROR(INDEX(Processos!$F$8:$F$17,MATCH(C123,Processos!$A$8:$A$17,0)),1) -> 1.084 | Q123: =IFERROR(INDEX(Matriz!$C$28:$C$33,MATCH(G123,Matriz!$A$28:$A$33,0)),0) -> 0 | R123: =IF(O123="","",ROUND(O123*P123+Q123,2)) -> 4.34 | S123: =IF(R123="","",IF(R123>=Matriz!$C$19,4,IF(R123>=Matriz!$C$18,3,IF(R123>=Matriz!$C$17,2,1)))) -> 4 | T123: =IF(S123="","",MAX(S123,IF(I123=5,Matriz!$C$23,0),IF(N123="Sim",Matriz!$C$24,0))) -> 4 | U123: =IF(T123="","",CHOOSE(T123,"Baixa","Normal","Alta","Urgente")) -> Urgente | V123: =IF(T123="","",T123*1000+R123*10-IF(H123="",3,H123)/10-ROW()/1000000) -> 4043.0999 | W123: =IF(V123="","",COUNTIF($V$5:$V$405,">"&V123)+1) -> 2 | X123: Âncora (proposta) | Y123: Procedimento para parar obra por segurança: risco à vida, norma de segurança e efeito direto na obra.
A124: 86aj0bje9 | B124: Elaborar POP - Processo de Reengenharia | C124: Engenharia | D124: Lucas Lopes | E124: em atraso | F124: 46265 | G124: Documento normativo | O124: =IF(COUNT(I124:M124)<5,"",ROUND((I124*Matriz!$C$5+J124*Matriz!$C$6+K124*Matriz!$C$7+L124*Matriz!$C$8+M124*Matriz!$C$9)/SUM(Matriz!$C$5:$C$9),2)) | P124: =IFERROR(INDEX(Processos!$F$8:$F$17,MATCH(C124,Processos!$A$8:$A$17,0)),1) -> 1.084 | Q124: =IFERROR(INDEX(Matriz!$C$28:$C$33,MATCH(G124,Matriz!$A$28:$A$33,0)),0) -> 0 | R124: =IF(O124="","",ROUND(O124*P124+Q124,2)) | S124: =IF(R124="","",IF(R124>=Matriz!$C$19,4,IF(R124>=Matriz!$C$18,3,IF(R124>=Matriz!$C$17,2,1)))) | T124: =IF(S124="","",MAX(S124,IF(I124=5,Matriz!$C$23,0),IF(N124="Sim",Matriz!$C$24,0))) | U124: =IF(T124="","",CHOOSE(T124,"Baixa","Normal","Alta","Urgente")) | V124: =IF(T124="","",T124*1000+R124*10-IF(H124="",3,H124)/10-ROW()/1000000) | W124: =IF(V124="","",COUNTIF($V$5:$V$405,">"&V124)+1)
A125: 86aj7c618 | B125: Elaborar POP - Processo de elaboração das viabilidades (Gadens e Make It | C125: Engenharia | D125: Eduardo Rosa | E125: em atraso | F125: 46265 | G125: Documento normativo | O125: =IF(COUNT(I125:M125)<5,"",ROUND((I125*Matriz!$C$5+J125*Matriz!$C$6+K125*Matriz!$C$7+L125*Matriz!$C$8+M125*Matriz!$C$9)/SUM(Matriz!$C$5:$C$9),2)) | P125: =IFERROR(INDEX(Processos!$F$8:$F$17,MATCH(C125,Processos!$A$8:$A$17,0)),1) -> 1.084 | Q125: =IFERROR(INDEX(Matriz!$C$28:$C$33,MATCH(G125,Matriz!$A$28:$A$33,0)),0) -> 0 | R125: =IF(O125="","",ROUND(O125*P125+Q125,2)) | S125: =IF(R125="","",IF(R125>=Matriz!$C$19,4,IF(R125>=Matriz!$C$18,3,IF(R125>=Matriz!$C$17,2,1)))) | T125: =IF(S125="","",MAX(S125,IF(I125=5,Matriz!$C$23,0),IF(N125="Sim",Matriz!$C$24,0))) | U125: =IF(T125="","",CHOOSE(T125,"Baixa","Normal","Alta","Urgente")) | V125: =IF(T125="","",T125*1000+R125*10-IF(H125="",3,H125)/10-ROW()/1000000) | W125: =IF(V125="","",COUNTIF($V$5:$V$405,">"&V125)+1)
A126: 86aj7bmyp | B126: Elaborar POP - Processo de integração de novos colaboradores de obra | C126: Engenharia | D126: Alessandro Braz | E126: em atraso | F126: 46295 | G126: Documento normativo | O126: =IF(COUNT(I126:M126)<5,"",ROUND((I126*Matriz!$C$5+J126*Matriz!$C$6+K126*Matriz!$C$7+L126*Matriz!$C$8+M126*Matriz!$C$9)/SUM(Matriz!$C$5:$C$9),2)) | P126: =IFERROR(INDEX(Processos!$F$8:$F$17,MATCH(C126,Processos!$A$8:$A$17,0)),1) -> 1.084 | Q126: =IFERROR(INDEX(Matriz!$C$28:$C$33,MATCH(G126,Matriz!$A$28:$A$33,0)),0) -> 0 | R126: =IF(O126="","",ROUND(O126*P126+Q126,2)) | S126: =IF(R126="","",IF(R126>=Matriz!$C$19,4,IF(R126>=Matriz!$C$18,3,IF(R126>=Matriz!$C$17,2,1)))) | T126: =IF(S126="","",MAX(S126,IF(I126=5,Matriz!$C$23,0),IF(N126="Sim",Matriz!$C$24,0))) | U126: =IF(T126="","",CHOOSE(T126,"Baixa","Normal","Alta","Urgente")) | V126: =IF(T126="","",T126*1000+R126*10-IF(H126="",3,H126)/10-ROW()/1000000) | W126: =IF(V126="","",COUNTIF($V$5:$V$405,">"&V126)+1)
A127: 86ahcknz7 | B127: Elaborar POP - Tratativas com base na avaliação – Plano de ação junto as áreas de GMO, Obra, Eng, e Qualidade (Alessandro) | C127: Engenharia | D127: Alessandro Braz | E127: em atraso | F127: 46234 | G127: Documento normativo | O127: =IF(COUNT(I127:M127)<5,"",ROUND((I127*Matriz!$C$5+J127*Matriz!$C$6+K127*Matriz!$C$7+L127*Matriz!$C$8+M127*Matriz!$C$9)/SUM(Matriz!$C$5:$C$9),2)) | P127: =IFERROR(INDEX(Processos!$F$8:$F$17,MATCH(C127,Processos!$A$8:$A$17,0)),1) -> 1.084 | Q127: =IFERROR(INDEX(Matriz!$C$28:$C$33,MATCH(G127,Matriz!$A$28:$A$33,0)),0) -> 0 | R127: =IF(O127="","",ROUND(O127*P127+Q127,2)) | S127: =IF(R127="","",IF(R127>=Matriz!$C$19,4,IF(R127>=Matriz!$C$18,3,IF(R127>=Matriz!$C$17,2,1)))) | T127: =IF(S127="","",MAX(S127,IF(I127=5,Matriz!$C$23,0),IF(N127="Sim",Matriz!$C$24,0))) | U127: =IF(T127="","",CHOOSE(T127,"Baixa","Normal","Alta","Urgente")) | V127: =IF(T127="","",T127*1000+R127*10-IF(H127="",3,H127)/10-ROW()/1000000) | W127: =IF(V127="","",COUNTIF($V$5:$V$405,">"&V127)+1)
A128: 86aj7bqh4 | B128: Elaborar Política - Segurança do Trabalho (Direitos, deveres e penalidades) | C128: Engenharia | D128: Alessandro Braz | E128: em atraso | F128: 46265 | G128: Documento normativo | O128: =IF(COUNT(I128:M128)<5,"",ROUND((I128*Matriz!$C$5+J128*Matriz!$C$6+K128*Matriz!$C$7+L128*Matriz!$C$8+M128*Matriz!$C$9)/SUM(Matriz!$C$5:$C$9),2)) | P128: =IFERROR(INDEX(Processos!$F$8:$F$17,MATCH(C128,Processos!$A$8:$A$17,0)),1) -> 1.084 | Q128: =IFERROR(INDEX(Matriz!$C$28:$C$33,MATCH(G128,Matriz!$A$28:$A$33,0)),0) -> 0 | R128: =IF(O128="","",ROUND(O128*P128+Q128,2)) | S128: =IF(R128="","",IF(R128>=Matriz!$C$19,4,IF(R128>=Matriz!$C$18,3,IF(R128>=Matriz!$C$17,2,1)))) | T128: =IF(S128="","",MAX(S128,IF(I128=5,Matriz!$C$23,0),IF(N128="Sim",Matriz!$C$24,0))) | U128: =IF(T128="","",CHOOSE(T128,"Baixa","Normal","Alta","Urgente")) | V128: =IF(T128="","",T128*1000+R128*10-IF(H128="",3,H128)/10-ROW()/1000000) | W128: =IF(V128="","",COUNTIF($V$5:$V$405,">"&V128)+1)
A129: 86ahckp2g | B129: Elaborar relatório de indicador de qualidade Gadens/Make-It – Incorporação e Projetos Complementares – Mariane | C129: Engenharia | D129: Mariane Cristine Machado Scandelari | E129: em atraso | F129: 46234 | G129: Definição ou decisão | O129: =IF(COUNT(I129:M129)<5,"",ROUND((I129*Matriz!$C$5+J129*Matriz!$C$6+K129*Matriz!$C$7+L129*Matriz!$C$8+M129*Matriz!$C$9)/SUM(Matriz!$C$5:$C$9),2)) | P129: =IFERROR(INDEX(Processos!$F$8:$F$17,MATCH(C129,Processos!$A$8:$A$17,0)),1) -> 1.084 | Q129: =IFERROR(INDEX(Matriz!$C$28:$C$33,MATCH(G129,Matriz!$A$28:$A$33,0)),0) -> 0 | R129: =IF(O129="","",ROUND(O129*P129+Q129,2)) | S129: =IF(R129="","",IF(R129>=Matriz!$C$19,4,IF(R129>=Matriz!$C$18,3,IF(R129>=Matriz!$C$17,2,1)))) | T129: =IF(S129="","",MAX(S129,IF(I129=5,Matriz!$C$23,0),IF(N129="Sim",Matriz!$C$24,0))) | U129: =IF(T129="","",CHOOSE(T129,"Baixa","Normal","Alta","Urgente")) | V129: =IF(T129="","",T129*1000+R129*10-IF(H129="",3,H129)/10-ROW()/1000000) | W129: =IF(V129="","",COUNTIF($V$5:$V$405,">"&V129)+1)
A130: 86ahckp0x | B130: Estruturar processo de rituais de gestão de obra (Helen) | C130: Engenharia | D130: Hellen Venturoso | E130: em atraso | F130: 46264 | G130: Definição ou decisão | O130: =IF(COUNT(I130:M130)<5,"",ROUND((I130*Matriz!$C$5+J130*Matriz!$C$6+K130*Matriz!$C$7+L130*Matriz!$C$8+M130*Matriz!$C$9)/SUM(Matriz!$C$5:$C$9),2)) | P130: =IFERROR(INDEX(Processos!$F$8:$F$17,MATCH(C130,Processos!$A$8:$A$17,0)),1) -> 1.084 | Q130: =IFERROR(INDEX(Matriz!$C$28:$C$33,MATCH(G130,Matriz!$A$28:$A$33,0)),0) -> 0 | R130: =IF(O130="","",ROUND(O130*P130+Q130,2)) | S130: =IF(R130="","",IF(R130>=Matriz!$C$19,4,IF(R130>=Matriz!$C$18,3,IF(R130>=Matriz!$C$17,2,1)))) | T130: =IF(S130="","",MAX(S130,IF(I130=5,Matriz!$C$23,0),IF(N130="Sim",Matriz!$C$24,0))) | U130: =IF(T130="","",CHOOSE(T130,"Baixa","Normal","Alta","Urgente")) | V130: =IF(T130="","",T130*1000+R130*10-IF(H130="",3,H130)/10-ROW()/1000000) | W130: =IF(V130="","",COUNTIF($V$5:$V$405,">"&V130)+1)
A131: 86aj811pt | B131: Implementar Indicador - % em valores negociados no início de obra (Make It) | C131: Engenharia | D131: Fernando de Souza, andressa.ferreira@makeitconstrutora.com.br | E131: em atraso | F131: 46265 | G131: Indicador | O131: =IF(COUNT(I131:M131)<5,"",ROUND((I131*Matriz!$C$5+J131*Matriz!$C$6+K131*Matriz!$C$7+L131*Matriz!$C$8+M131*Matriz!$C$9)/SUM(Matriz!$C$5:$C$9),2)) | P131: =IFERROR(INDEX(Processos!$F$8:$F$17,MATCH(C131,Processos!$A$8:$A$17,0)),1) -> 1.084 | Q131: =IFERROR(INDEX(Matriz!$C$28:$C$33,MATCH(G131,Matriz!$A$28:$A$33,0)),0) -> -0.3 | R131: =IF(O131="","",ROUND(O131*P131+Q131,2)) | S131: =IF(R131="","",IF(R131>=Matriz!$C$19,4,IF(R131>=Matriz!$C$18,3,IF(R131>=Matriz!$C$17,2,1)))) | T131: =IF(S131="","",MAX(S131,IF(I131=5,Matriz!$C$23,0),IF(N131="Sim",Matriz!$C$24,0))) | U131: =IF(T131="","",CHOOSE(T131,"Baixa","Normal","Alta","Urgente")) | V131: =IF(T131="","",T131*1000+R131*10-IF(H131="",3,H131)/10-ROW()/1000000) | W131: =IF(V131="","",COUNTIF($V$5:$V$405,">"&V131)+1)
A132: 86aj7etg6 | B132: Implementar Indicador - Desvio de Orçamento Lançamento e Due | C132: Engenharia | D132: Leticia Gonçalves Bacchi | E132: em atraso | F132: 46265 | G132: Indicador | O132: =IF(COUNT(I132:M132)<5,"",ROUND((I132*Matriz!$C$5+J132*Matriz!$C$6+K132*Matriz!$C$7+L132*Matriz!$C$8+M132*Matriz!$C$9)/SUM(Matriz!$C$5:$C$9),2)) | P132: =IFERROR(INDEX(Processos!$F$8:$F$17,MATCH(C132,Processos!$A$8:$A$17,0)),1) -> 1.084 | Q132: =IFERROR(INDEX(Matriz!$C$28:$C$33,MATCH(G132,Matriz!$A$28:$A$33,0)),0) -> -0.3 | R132: =IF(O132="","",ROUND(O132*P132+Q132,2)) | S132: =IF(R132="","",IF(R132>=Matriz!$C$19,4,IF(R132>=Matriz!$C$18,3,IF(R132>=Matriz!$C$17,2,1)))) | T132: =IF(S132="","",MAX(S132,IF(I132=5,Matriz!$C$23,0),IF(N132="Sim",Matriz!$C$24,0))) | U132: =IF(T132="","",CHOOSE(T132,"Baixa","Normal","Alta","Urgente")) | V132: =IF(T132="","",T132*1000+R132*10-IF(H132="",3,H132)/10-ROW()/1000000) | W132: =IF(V132="","",COUNTIF($V$5:$V$405,">"&V132)+1)
A133: 86aj7etg3 | B133: Implementar Indicador - Desvio de Orçamento na Due/Paramétrico m² | C133: Engenharia | D133: Leticia Gonçalves Bacchi | E133: em atraso | F133: 46265 | G133: Indicador | O133: =IF(COUNT(I133:M133)<5,"",ROUND((I133*Matriz!$C$5+J133*Matriz!$C$6+K133*Matriz!$C$7+L133*Matriz!$C$8+M133*Matriz!$C$9)/SUM(Matriz!$C$5:$C$9),2)) | P133: =IFERROR(INDEX(Processos!$F$8:$F$17,MATCH(C133,Processos!$A$8:$A$17,0)),1) -> 1.084 | Q133: =IFERROR(INDEX(Matriz!$C$28:$C$33,MATCH(G133,Matriz!$A$28:$A$33,0)),0) -> -0.3 | R133: =IF(O133="","",ROUND(O133*P133+Q133,2)) | S133: =IF(R133="","",IF(R133>=Matriz!$C$19,4,IF(R133>=Matriz!$C$18,3,IF(R133>=Matriz!$C$17,2,1)))) | T133: =IF(S133="","",MAX(S133,IF(I133=5,Matriz!$C$23,0),IF(N133="Sim",Matriz!$C$24,0))) | U133: =IF(T133="","",CHOOSE(T133,"Baixa","Normal","Alta","Urgente")) | V133: =IF(T133="","",T133*1000+R133*10-IF(H133="",3,H133)/10-ROW()/1000000) | W133: =IF(V133="","",COUNTIF($V$5:$V$405,">"&V133)+1)
A134: 86aj7e6rc | B134: Implementar Indicador - Qualidade do Projeto (AP) | C134: Engenharia | D134: Lucas Lopes | E134: em atraso | F134: 46265 | G134: Indicador | O134: =IF(COUNT(I134:M134)<5,"",ROUND((I134*Matriz!$C$5+J134*Matriz!$C$6+K134*Matriz!$C$7+L134*Matriz!$C$8+M134*Matriz!$C$9)/SUM(Matriz!$C$5:$C$9),2)) | P134: =IFERROR(INDEX(Processos!$F$8:$F$17,MATCH(C134,Processos!$A$8:$A$17,0)),1) -> 1.084 | Q134: =IFERROR(INDEX(Matriz!$C$28:$C$33,MATCH(G134,Matriz!$A$28:$A$33,0)),0) -> -0.3 | R134: =IF(O134="","",ROUND(O134*P134+Q134,2)) | S134: =IF(R134="","",IF(R134>=Matriz!$C$19,4,IF(R134>=Matriz!$C$18,3,IF(R134>=Matriz!$C$17,2,1)))) | T134: =IF(S134="","",MAX(S134,IF(I134=5,Matriz!$C$23,0),IF(N134="Sim",Matriz!$C$24,0))) | U134: =IF(T134="","",CHOOSE(T134,"Baixa","Normal","Alta","Urgente")) | V134: =IF(T134="","",T134*1000+R134*10-IF(H134="",3,H134)/10-ROW()/1000000) | W134: =IF(V134="","",COUNTIF($V$5:$V$405,">"&V134)+1)
A135: 86aj7cq1g | B135: Implementar Indicador - Qualidade do Projeto (EP) | C135: Engenharia | D135: Lucas Lopes | E135: em atraso | F135: 46265 | G135: Indicador | O135: =IF(COUNT(I135:M135)<5,"",ROUND((I135*Matriz!$C$5+J135*Matriz!$C$6+K135*Matriz!$C$7+L135*Matriz!$C$8+M135*Matriz!$C$9)/SUM(Matriz!$C$5:$C$9),2)) | P135: =IFERROR(INDEX(Processos!$F$8:$F$17,MATCH(C135,Processos!$A$8:$A$17,0)),1) -> 1.084 | Q135: =IFERROR(INDEX(Matriz!$C$28:$C$33,MATCH(G135,Matriz!$A$28:$A$33,0)),0) -> -0.3 | R135: =IF(O135="","",ROUND(O135*P135+Q135,2)) | S135: =IF(R135="","",IF(R135>=Matriz!$C$19,4,IF(R135>=Matriz!$C$18,3,IF(R135>=Matriz!$C$17,2,1)))) | T135: =IF(S135="","",MAX(S135,IF(I135=5,Matriz!$C$23,0),IF(N135="Sim",Matriz!$C$24,0))) | U135: =IF(T135="","",CHOOSE(T135,"Baixa","Normal","Alta","Urgente")) | V135: =IF(T135="","",T135*1000+R135*10-IF(H135="",3,H135)/10-ROW()/1000000) | W135: =IF(V135="","",COUNTIF($V$5:$V$405,">"&V135)+1)
... A174: 86ahckp0f | B174: Validação diária de quantitativos (revisão projeto e alinhamento junto ao orçamento (Helen) | C174: Engenharia | D174: Hellen Venturoso | E174: em progresso | F174: 46418 | G174: Definição ou decisão | O174: =IF(COUNT(I174:M174)<5,"",ROUND((I174*Matriz!$C$5+J174*Matriz!$C$6+K174*Matriz!$C$7+L174*Matriz!$C$8+M174*Matriz!$C$9)/SUM(Matriz!$C$5:$C$9),2)) | P174: =IFERROR(INDEX(Processos!$F$8:$F$17,MATCH(C174,Processos!$A$8:$A$17,0)),1) -> 1.084 | Q174: =IFERROR(INDEX(Matriz!$C$28:$C$33,MATCH(G174,Matriz!$A$28:$A$33,0)),0) -> 0 | R174: =IF(O174="","",ROUND(O174*P174+Q174,2)) | S174: =IF(R174="","",IF(R174>=Matriz!$C$19,4,IF(R174>=Matriz!$C$18,3,IF(R174>=Matriz!$C$17,2,1)))) | T174: =IF(S174="","",MAX(S174,IF(I174=5,Matriz!$C$23,0),IF(N174="Sim",Matriz!$C$24,0))) | U174: =IF(T174="","",CHOOSE(T174,"Baixa","Normal","Alta","Urgente")) | V174: =IF(T174="","",T174*1000+R174*10-IF(H174="",3,H174)/10-ROW()/1000000) | W174: =IF(V174="","",COUNTIF($V$5:$V$405,">"&V174)+1)
A175: 17tpepcmy78 | B175: Alinhar com Mega sobre integrações para realizar planejamento de compras | C175: Engenharia | D175: Alexandre Marchiori Cruz | E175: sem prazo definido | G175: Automação ou sistema | O175: =IF(COUNT(I175:M175)<5,"",ROUND((I175*Matriz!$C$5+J175*Matriz!$C$6+K175*Matriz!$C$7+L175*Matriz!$C$8+M175*Matriz!$C$9)/SUM(Matriz!$C$5:$C$9),2)) | P175: =IFERROR(INDEX(Processos!$F$8:$F$17,MATCH(C175,Processos!$A$8:$A$17,0)),1) -> 1.084 | Q175: =IFERROR(INDEX(Matriz!$C$28:$C$33,MATCH(G175,Matriz!$A$28:$A$33,0)),0) -> 0 | R175: =IF(O175="","",ROUND(O175*P175+Q175,2)) | S175: =IF(R175="","",IF(R175>=Matriz!$C$19,4,IF(R175>=Matriz!$C$18,3,IF(R175>=Matriz!$C$17,2,1)))) | T175: =IF(S175="","",MAX(S175,IF(I175=5,Matriz!$C$23,0),IF(N175="Sim",Matriz!$C$24,0))) | U175: =IF(T175="","",CHOOSE(T175,"Baixa","Normal","Alta","Urgente")) | V175: =IF(T175="","",T175*1000+R175*10-IF(H175="",3,H175)/10-ROW()/1000000) | W175: =IF(V175="","",COUNTIF($V$5:$V$405,">"&V175)+1)
A176: 86agnzdx8 | B176: Analisar e implantar banco de dados de preços unitários em plataforma que atenda a demanda | C176: Engenharia | D176: Alexandre Marchiori Cruz | E176: sem prazo definido | G176: Automação ou sistema | O176: =IF(COUNT(I176:M176)<5,"",ROUND((I176*Matriz!$C$5+J176*Matriz!$C$6+K176*Matriz!$C$7+L176*Matriz!$C$8+M176*Matriz!$C$9)/SUM(Matriz!$C$5:$C$9),2)) | P176: =IFERROR(INDEX(Processos!$F$8:$F$17,MATCH(C176,Processos!$A$8:$A$17,0)),1) -> 1.084 | Q176: =IFERROR(INDEX(Matriz!$C$28:$C$33,MATCH(G176,Matriz!$A$28:$A$33,0)),0) -> 0 | R176: =IF(O176="","",ROUND(O176*P176+Q176,2)) | S176: =IF(R176="","",IF(R176>=Matriz!$C$19,4,IF(R176>=Matriz!$C$18,3,IF(R176>=Matriz!$C$17,2,1)))) | T176: =IF(S176="","",MAX(S176,IF(I176=5,Matriz!$C$23,0),IF(N176="Sim",Matriz!$C$24,0))) | U176: =IF(T176="","",CHOOSE(T176,"Baixa","Normal","Alta","Urgente")) | V176: =IF(T176="","",T176*1000+R176*10-IF(H176="",3,H176)/10-ROW()/1000000) | W176: =IF(V176="","",COUNTIF($V$5:$V$405,">"&V176)+1)
A177: 86agdwca5 | B177: Análise da possibilidade de rateio da coordenação de obras | C177: Engenharia | D177: Paulo Tavares | E177: sem prazo definido | G177: Definição ou decisão | O177: =IF(COUNT(I177:M177)<5,"",ROUND((I177*Matriz!$C$5+J177*Matriz!$C$6+K177*Matriz!$C$7+L177*Matriz!$C$8+M177*Matriz!$C$9)/SUM(Matriz!$C$5:$C$9),2)) | P177: =IFERROR(INDEX(Processos!$F$8:$F$17,MATCH(C177,Processos!$A$8:$A$17,0)),1) -> 1.084 | Q177: =IFERROR(INDEX(Matriz!$C$28:$C$33,MATCH(G177,Matriz!$A$28:$A$33,0)),0) -> 0 | R177: =IF(O177="","",ROUND(O177*P177+Q177,2)) | S177: =IF(R177="","",IF(R177>=Matriz!$C$19,4,IF(R177>=Matriz!$C$18,3,IF(R177>=Matriz!$C$17,2,1)))) | T177: =IF(S177="","",MAX(S177,IF(I177=5,Matriz!$C$23,0),IF(N177="Sim",Matriz!$C$24,0))) | U177: =IF(T177="","",CHOOSE(T177,"Baixa","Normal","Alta","Urgente")) | V177: =IF(T177="","",T177*1000+R177*10-IF(H177="",3,H177)/10-ROW()/1000000) | W177: =IF(V177="","",COUNTIF($V$5:$V$405,">"&V177)+1)
A178: 86age4cnw | B178: Avaliar automação do processo de Pré-Planejamento (BD de Indices - Formulário / Prompt) | C178: Engenharia | D178: Fernando Okraska, Leticia Gonçalves Bacchi | E178: sem prazo definido | G178: Definição ou decisão | O178: =IF(COUNT(I178:M178)<5,"",ROUND((I178*Matriz!$C$5+J178*Matriz!$C$6+K178*Matriz!$C$7+L178*Matriz!$C$8+M178*Matriz!$C$9)/SUM(Matriz!$C$5:$C$9),2)) | P178: =IFERROR(INDEX(Processos!$F$8:$F$17,MATCH(C178,Processos!$A$8:$A$17,0)),1) -> 1.084 | Q178: =IFERROR(INDEX(Matriz!$C$28:$C$33,MATCH(G178,Matriz!$A$28:$A$33,0)),0) -> 0 | R178: =IF(O178="","",ROUND(O178*P178+Q178,2)) | S178: =IF(R178="","",IF(R178>=Matriz!$C$19,4,IF(R178>=Matriz!$C$18,3,IF(R178>=Matriz!$C$17,2,1)))) | T178: =IF(S178="","",MAX(S178,IF(I178=5,Matriz!$C$23,0),IF(N178="Sim",Matriz!$C$24,0))) | U178: =IF(T178="","",CHOOSE(T178,"Baixa","Normal","Alta","Urgente")) | V178: =IF(T178="","",T178*1000+R178*10-IF(H178="",3,H178)/10-ROW()/1000000) | W178: =IF(V178="","",COUNTIF($V$5:$V$405,">"&V178)+1)
A179: 17tpepcgt64 | B179: Avaliar plataforma para substituição do BPM | C179: Engenharia | D179: Alexandre Marchiori Cruz | E179: sem prazo definido | G179: Automação ou sistema | O179: =IF(COUNT(I179:M179)<5,"",ROUND((I179*Matriz!$C$5+J179*Matriz!$C$6+K179*Matriz!$C$7+L179*Matriz!$C$8+M179*Matriz!$C$9)/SUM(Matriz!$C$5:$C$9),2)) | P179: =IFERROR(INDEX(Processos!$F$8:$F$17,MATCH(C179,Processos!$A$8:$A$17,0)),1) -> 1.084 | Q179: =IFERROR(INDEX(Matriz!$C$28:$C$33,MATCH(G179,Matriz!$A$28:$A$33,0)),0) -> 0 | R179: =IF(O179="","",ROUND(O179*P179+Q179,2)) | S179: =IF(R179="","",IF(R179>=Matriz!$C$19,4,IF(R179>=Matriz!$C$18,3,IF(R179>=Matriz!$C$17,2,1)))) | T179: =IF(S179="","",MAX(S179,IF(I179=5,Matriz!$C$23,0),IF(N179="Sim",Matriz!$C$24,0))) | U179: =IF(T179="","",CHOOSE(T179,"Baixa","Normal","Alta","Urgente")) | V179: =IF(T179="","",T179*1000+R179*10-IF(H179="",3,H179)/10-ROW()/1000000) | W179: =IF(V179="","",COUNTIF($V$5:$V$405,">"&V179)+1)
A180: 86agedpc9 | B180: Avaliar se há possibilidade de alterar de uma SM para SC e apropriação de consumo de material por item de serviço (ex. Laje) | C180: Engenharia | D180: Alexandre Marchiori Cruz | E180: sem prazo definido | G180: Definição ou decisão | O180: =IF(COUNT(I180:M180)<5,"",ROUND((I180*Matriz!$C$5+J180*Matriz!$C$6+K180*Matriz!$C$7+L180*Matriz!$C$8+M180*Matriz!$C$9)/SUM(Matriz!$C$5:$C$9),2)) | P180: =IFERROR(INDEX(Processos!$F$8:$F$17,MATCH(C180,Processos!$A$8:$A$17,0)),1) -> 1.084 | Q180: =IFERROR(INDEX(Matriz!$C$28:$C$33,MATCH(G180,Matriz!$A$28:$A$33,0)),0) -> 0 | R180: =IF(O180="","",ROUND(O180*P180+Q180,2)) | S180: =IF(R180="","",IF(R180>=Matriz!$C$19,4,IF(R180>=Matriz!$C$18,3,IF(R180>=Matriz!$C$17,2,1)))) | T180: =IF(S180="","",MAX(S180,IF(I180=5,Matriz!$C$23,0),IF(N180="Sim",Matriz!$C$24,0))) | U180: =IF(T180="","",CHOOSE(T180,"Baixa","Normal","Alta","Urgente")) | V180: =IF(T180="","",T180*1000+R180*10-IF(H180="",3,H180)/10-ROW()/1000000) | W180: =IF(V180="","",COUNTIF($V$5:$V$405,">"&V180)+1)
...
